Workbook

Sheet Dashboard
B1: ASEGURADORA ANCÓN, S.A. – DASHBOARD DE RIESGO PBC/FT/FPADM – EVALUACIÓN INDEPENDIENTE 2024-2025
B2: Período: 1 julio 2024 – 30 junio 2025 | Fuente: Informe Final PBC – AA | Todas las cifras se calculan con fórmulas desde las hojas Riesgos y Plan de Acción
B4: TOTAL BRECHAS | C4: CRÍTICO | E4: MEDIO-ALTO | G4: MEDIO | I4: BAJO | L4: OPORT. MEJORA (OM+RM) | N4: ACCIONES PLAN (PA) | P4: TOTAL REGISTROS
B5: =COUNTIF(Riesgos!$B$4:$B$89,"Brecha") -> 59 | C5: =COUNTIF(Riesgos!$J$4:$J$89,"CRÍTICO") -> 8 | E5: =COUNTIF(Riesgos!$J$4:$J$89,"MEDIO-ALTO") -> 22 | G5: =COUNTIF(Riesgos!$J$4:$J$89,"MEDIO") -> 27 | I5: =COUNTIF(Riesgos!$J$4:$J$89,"BAJO") -> 2 | L5: =COUNTIF(Riesgos!$B$4:$B$89,"Oportunidad de Mejora") -> 27 | N5: =COUNTA('Plan de Acción'!$A$4:$A$34) -> 31 | P5: =COUNTA(Riesgos!$A$4:$A$89) -> 86
B7: CALIFICACIÓN POR COMPONENTE (regla del informe: ≥2 CRÍTICO = Nivel 1; 1 CRÍTICO o ≥3 MEDIO-ALTO = Nivel 2; 1-2 MEDIO-ALTO = Nivel 3; resto = Nivel 4) | L7: MAPA DE CALOR – BRECHAS (P × I)
B8: Componente | C8: CRÍTICO | D8: MEDIO-ALTO | E8: MEDIO | F8: BAJO | G8: TOTAL | H8: P×I promedio | I8: P×I máximo | J8: Calificación del componente | L8: PROB. ↓ / IMP. → | M8: 1 Insignificante | N8: 2 Menor | O8: 3 Moderado | P8: 4 Mayor | Q8: 5 Catastrófico
B9: Gobierno Corporativo | C9: =COUNTIFS(Riesgos!$K$4:$K$89,$B9,Riesgos!$J$4:$J$89,"CRÍTICO") -> 1 | D9: =COUNTIFS(Riesgos!$K$4:$K$89,$B9,Riesgos!$J$4:$J$89,"MEDIO-ALTO") -> 5 | E9: =COUNTIFS(Riesgos!$K$4:$K$89,$B9,Riesgos!$J$4:$J$89,"MEDIO") -> 5 | F9: =COUNTIFS(Riesgos!$K$4:$K$89,$B9,Riesgos!$J$4:$J$89,"BAJO") -> 0 | G9: =SUM(C9:F9) -> 11 | H9: =IFERROR(AVERAGEIFS(Riesgos!$M$4:$M$89,Riesgos!$K$4:$K$89,$B9),0) -> 8.5454545 | I9: =_xlfn.MAXIFS(Riesgos!$M$4:$M$89,Riesgos!$K$4:$K$89,$B9) -> 16 | J9: =IF(C9>=2,"Nivel 1 – CRÍTICO (No Cumple)",IF(OR(C9=1,D9>=3),"Nivel 2 – ALTO (Brecha Mayor)",IF(D9>=1,"Nivel 3 – MEDIO (Brecha Parcial)","Nivel 4 – BAJO (Cumple)"))) -> Nivel 2 – ALTO (Brecha Mayor) | L9: 5 Frecuente | M9: =COUNTIFS(Riesgos!$F$4:$F$89,5,Riesgos!$H$4:$H$89,1,Riesgos!$B$4:$B$89,"Brecha") -> 0 | N9: =COUNTIFS(Riesgos!$F$4:$F$89,5,Riesgos!$H$4:$H$89,2,Riesgos!$B$4:$B$89,"Brecha") -> 0 | O9: =COUNTIFS(Riesgos!$F$4:$F$89,5,Riesgos!$H$4:$H$89,3,Riesgos!$B$4:$B$89,"Brecha") -> 1 | P9: =COUNTIFS(Riesgos!$F$4:$F$89,5,Riesgos!$H$4:$H$89,4,Riesgos!$B$4:$B$89,"Brecha") -> 1 | Q9: =COUNTIFS(Riesgos!$F$4:$F$89,5,Riesgos!$H$4:$H$89,5,Riesgos!$B$4:$B$89,"Brecha") -> 0
B10: Políticas y Procedimientos | C10: =COUNTIFS(Riesgos!$K$4:$K$89,$B10,Riesgos!$J$4:$J$89,"CRÍTICO") -> 0 | D10: =COUNTIFS(Riesgos!$K$4:$K$89,$B10,Riesgos!$J$4:$J$89,"MEDIO-ALTO") -> 2 | E10: =COUNTIFS(Riesgos!$K$4:$K$89,$B10,Riesgos!$J$4:$J$89,"MEDIO") -> 7 | F10: =COUNTIFS(Riesgos!$K$4:$K$89,$B10,Riesgos!$J$4:$J$89,"BAJO") -> 1 | G10: =SUM(C10:F10) -> 10 | H10: =IFERROR(AVERAGEIFS(Riesgos!$M$4:$M$89,Riesgos!$K$4:$K$89,$B10),0) -> 6 | I10: =_xlfn.MAXIFS(Riesgos!$M$4:$M$89,Riesgos!$K$4:$K$89,$B10) -> 9 | J10: =IF(C10>=2,"Nivel 1 – CRÍTICO (No Cumple)",IF(OR(C10=1,D10>=3),"Nivel 2 – ALTO (Brecha Mayor)",IF(D10>=1,"Nivel 3 – MEDIO (Brecha Parcial)","Nivel 4 – BAJO (Cumple)"))) -> Nivel 3 – MEDIO (Brecha Parcial) | L10: 4 Probable | M10: =COUNTIFS(Riesgos!$F$4:$F$89,4,Riesgos!$H$4:$H$89,1,Riesgos!$B$4:$B$89,"Brecha") -> 0 | N10: =COUNTIFS(Riesgos!$F$4:$F$89,4,Riesgos!$H$4:$H$89,2,Riesgos!$B$4:$B$89,"Brecha") -> 0 | O10: =COUNTIFS(Riesgos!$F$4:$F$89,4,Riesgos!$H$4:$H$89,3,Riesgos!$B$4:$B$89,"Brecha") -> 6 | P10: =COUNTIFS(Riesgos!$F$4:$F$89,4,Riesgos!$H$4:$H$89,4,Riesgos!$B$4:$B$89,"Brecha") -> 5 | Q10: =COUNTIFS(Riesgos!$F$4:$F$89,4,Riesgos!$H$4:$H$89,5,Riesgos!$B$4:$B$89,"Brecha") -> 0
B11: Programa Anual de Cumplimiento | C11: =COUNTIFS(Riesgos!$K$4:$K$89,$B11,Riesgos!$J$4:$J$89,"CRÍTICO") -> 0 | D11: =COUNTIFS(Riesgos!$K$4:$K$89,$B11,Riesgos!$J$4:$J$89,"MEDIO-ALTO") -> 2 | E11: =COUNTIFS(Riesgos!$K$4:$K$89,$B11,Riesgos!$J$4:$J$89,"MEDIO") -> 4 | F11: =COUNTIFS(Riesgos!$K$4:$K$89,$B11,Riesgos!$J$4:$J$89,"BAJO") -> 0 | G11: =SUM(C11:F11) -> 6 | H11: =IFERROR(AVERAGEIFS(Riesgos!$M$4:$M$89,Riesgos!$K$4:$K$89,$B11),0) -> 6.6666667 | I11: =_xlfn.MAXIFS(Riesgos!$M$4:$M$89,Riesgos!$K$4:$K$89,$B11) -> 9 | J11: =IF(C11>=2,"Nivel 1 – CRÍTICO (No Cumple)",IF(OR(C11=1,D11>=3),"Nivel 2 – ALTO (Brecha Mayor)",IF(D11>=1,"Nivel 3 – MEDIO (Brecha Parcial)","Nivel 4 – BAJO (Cumple)"))) -> Nivel 3 – MEDIO (Brecha Parcial) | L11: 3 Ocasional | M11: =COUNTIFS(Riesgos!$F$4:$F$89,3,Riesgos!$H$4:$H$89,1,Riesgos!$B$4:$B$89,"Brecha") -> 0 | N11: =COUNTIFS(Riesgos!$F$4:$F$89,3,Riesgos!$H$4:$H$89,2,Riesgos!$B$4:$B$89,"Brecha") -> 11 | O11: =COUNTIFS(Riesgos!$F$4:$F$89,3,Riesgos!$H$4:$H$89,3,Riesgos!$B$4:$B$89,"Brecha") -> 14 | P11: =COUNTIFS(Riesgos!$F$4:$F$89,3,Riesgos!$H$4:$H$89,4,Riesgos!$B$4:$B$89,"Brecha") -> 1 | Q11: =COUNTIFS(Riesgos!$F$4:$F$89,3,Riesgos!$H$4:$H$89,5,Riesgos!$B$4:$B$89,"Brecha") -> 1
B12: Monitoreo Transaccional | C12: =COUNTIFS(Riesgos!$K$4:$K$89,$B12,Riesgos!$J$4:$J$89,"CRÍTICO") -> 1 | D12: =COUNTIFS(Riesgos!$K$4:$K$89,$B12,Riesgos!$J$4:$J$89,"MEDIO-ALTO") -> 5 | E12: =COUNTIFS(Riesgos!$K$4:$K$89,$B12,Riesgos!$J$4:$J$89,"MEDIO") -> 1 | F12: =COUNTIFS(Riesgos!$K$4:$K$89,$B12,Riesgos!$J$4:$J$89,"BAJO") -> 1 | G12: =SUM(C12:F12) -> 8 | H12: =IFERROR(AVERAGEIFS(Riesgos!$M$4:$M$89,Riesgos!$K$4:$K$89,$B12),0) -> 9.5 | I12: =_xlfn.MAXIFS(Riesgos!$M$4:$M$89,Riesgos!$K$4:$K$89,$B12) -> 16 | J12: =IF(C12>=2,"Nivel 1 – CRÍTICO (No Cumple)",IF(OR(C12=1,D12>=3),"Nivel 2 – ALTO (Brecha Mayor)",IF(D12>=1,"Nivel 3 – MEDIO (Brecha Parcial)","Nivel 4 – BAJO (Cumple)"))) -> Nivel 2 – ALTO (Brecha Mayor) | L12: 2 Posible | M12: =COUNTIFS(Riesgos!$F$4:$F$89,2,Riesgos!$H$4:$H$89,1,Riesgos!$B$4:$B$89,"Brecha") -> 1 | N12: =COUNTIFS(Riesgos!$F$4:$F$89,2,Riesgos!$H$4:$H$89,2,Riesgos!$B$4:$B$89,"Brecha") -> 7 | O12: =COUNTIFS(Riesgos!$F$4:$F$89,2,Riesgos!$H$4:$H$89,3,Riesgos!$B$4:$B$89,"Brecha") -> 9 | P12: =COUNTIFS(Riesgos!$F$4:$F$89,2,Riesgos!$H$4:$H$89,4,Riesgos!$B$4:$B$89,"Brecha") -> 1 | Q12: =COUNTIFS(Riesgos!$F$4:$F$89,2,Riesgos!$H$4:$H$89,5,Riesgos!$B$4:$B$89,"Brecha") -> 0
B13: Debida Diligencia | C13: =COUNTIFS(Riesgos!$K$4:$K$89,$B13,Riesgos!$J$4:$J$89,"CRÍTICO") -> 3 | D13: =COUNTIFS(Riesgos!$K$4:$K$89,$B13,Riesgos!$J$4:$J$89,"MEDIO-ALTO") -> 4 | E13: =COUNTIFS(Riesgos!$K$4:$K$89,$B13,Riesgos!$J$4:$J$89,"MEDIO") -> 1 | F13: =COUNTIFS(Riesgos!$K$4:$K$89,$B13,Riesgos!$J$4:$J$89,"BAJO") -> 0 | G13: =SUM(C13:F13) -> 8 | H13: =IFERROR(AVERAGEIFS(Riesgos!$M$4:$M$89,Riesgos!$K$4:$K$89,$B13),0) -> 11.875 | I13: =_xlfn.MAXIFS(Riesgos!$M$4:$M$89,Riesgos!$K$4:$K$89,$B13) -> 20 | J13: =IF(C13>=2,"Nivel 1 – CRÍTICO (No Cumple)",IF(OR(C13=1,D13>=3),"Nivel 2 – ALTO (Brecha Mayor)",IF(D13>=1,"Nivel 3 – MEDIO (Brecha Parcial)","Nivel 4 – BAJO (Cumple)"))) -> Nivel 1 – CRÍTICO (No Cumple) | L13: 1 Improbable | M13: =COUNTIFS(Riesgos!$F$4:$F$89,1,Riesgos!$H$4:$H$89,1,Riesgos!$B$4:$B$89,"Brecha") -> 0 | N13: =COUNTIFS(Riesgos!$F$4:$F$89,1,Riesgos!$H$4:$H$89,2,Riesgos!$B$4:$B$89,"Brecha") -> 1 | O13: =COUNTIFS(Riesgos!$F$4:$F$89,1,Riesgos!$H$4:$H$89,3,Riesgos!$B$4:$B$89,"Brecha") -> 0 | P13: =COUNTIFS(Riesgos!$F$4:$F$89,1,Riesgos!$H$4:$H$89,4,Riesgos!$B$4:$B$89,"Brecha") -> 0 | Q13: =COUNTIFS(Riesgos!$F$4:$F$89,1,Riesgos!$H$4:$H$89,5,Riesgos!$B$4:$B$89,"Brecha") -> 0
B14: Evaluación de Riesgo AML | C14: =COUNTIFS(Riesgos!$K$4:$K$89,$B14,Riesgos!$J$4:$J$89,"CRÍTICO") -> 1 | D14: =COUNTIFS(Riesgos!$K$4:$K$89,$B14,Riesgos!$J$4:$J$89,"MEDIO-ALTO") -> 1 | E14: =COUNTIFS(Riesgos!$K$4:$K$89,$B14,Riesgos!$J$4:$J$89,"MEDIO") -> 3 | F14: =COUNTIFS(Riesgos!$K$4:$K$89,$B14,Riesgos!$J$4:$J$89,"BAJO") -> 0 | G14: =SUM(C14:F14) -> 5 | H14: =IFERROR(AVERAGEIFS(Riesgos!$M$4:$M$89,Riesgos!$K$4:$K$89,$B14),0) -> 7.8 | I14: =_xlfn.MAXIFS(Riesgos!$M$4:$M$89,Riesgos!$K$4:$K$89,$B14) -> 16 | J14: =IF(C14>=2,"Nivel 1 – CRÍTICO (No Cumple)",IF(OR(C14=1,D14>=3),"Nivel 2 – ALTO (Brecha Mayor)",IF(D14>=1,"Nivel 3 – MEDIO (Brecha Parcial)","Nivel 4 – BAJO (Cumple)"))) -> Nivel 2 – ALTO (Brecha Mayor) | L14: Ceros = sin brechas en la celda. Los colores siguen la tabla de niveles de la hoja Variables.
B15: Reportes Regulatorios | C15: =COUNTIFS(Riesgos!$K$4:$K$89,$B15,Riesgos!$J$4:$J$89,"CRÍTICO") -> 2 | D15: =COUNTIFS(Riesgos!$K$4:$K$89,$B15,Riesgos!$J$4:$J$89,"MEDIO-ALTO") -> 2 | E15: =COUNTIFS(Riesgos!$K$4:$K$89,$B15,Riesgos!$J$4:$J$89,"MEDIO") -> 2 | F15: =COUNTIFS(Riesgos!$K$4:$K$89,$B15,Riesgos!$J$4:$J$89,"BAJO") -> 0 | G15: =SUM(C15:F15) -> 6 | H15: =IFERROR(AVERAGEIFS(Riesgos!$M$4:$M$89,Riesgos!$K$4:$K$89,$B15),0) -> 10.333333 | I15: =_xlfn.MAXIFS(Riesgos!$M$4:$M$89,Riesgos!$K$4:$K$89,$B15) -> 16 | J15: =IF(C15>=2,"Nivel 1 – CRÍTICO (No Cumple)",IF(OR(C15=1,D15>=3),"Nivel 2 – ALTO (Brecha Mayor)",IF(D15>=1,"Nivel 3 – MEDIO (Brecha Parcial)","Nivel 4 – BAJO (Cumple)"))) -> Nivel 1 – CRÍTICO (No Cumple)
B16: Conservación de Documentos | C16: =COUNTIFS(Riesgos!$K$4:$K$89,$B16,Riesgos!$J$4:$J$89,"CRÍTICO") -> 0 | D16: =COUNTIFS(Riesgos!$K$4:$K$89,$B16,Riesgos!$J$4:$J$89,"MEDIO-ALTO") -> 1 | E16: =COUNTIFS(Riesgos!$K$4:$K$89,$B16,Riesgos!$J$4:$J$89,"MEDIO") -> 4 | F16: =COUNTIFS(Riesgos!$K$4:$K$89,$B16,Riesgos!$J$4:$J$89,"BAJO") -> 0 | G16: =SUM(C16:F16) -> 5 | H16: =IFERROR(AVERAGEIFS(Riesgos!$M$4:$M$89,Riesgos!$K$4:$K$89,$B16),0) -> 6.8 | I16: =_xlfn.MAXIFS(Riesgos!$M$4:$M$89,Riesgos!$K$4:$K$89,$B16) -> 12 | J16: =IF(C16>=2,"Nivel 1 – CRÍTICO (No Cumple)",IF(OR(C16=1,D16>=3),"Nivel 2 – ALTO (Brecha Mayor)",IF(D16>=1,"Nivel 3 – MEDIO (Brecha Parcial)","Nivel 4 – BAJO (Cumple)"))) -> Nivel 3 – MEDIO (Brecha Parcial) | L16: PLAN DE ACCIÓN POR PRIORIDAD | O16: HOJA DE RUTA ACUERDO 07-2025
B17: TOTAL | C17: =SUM(C9:C16) -> 8 | D17: =SUM(D9:D16) -> 22 | E17: =SUM(E9:E16) -> 27 | F17: =SUM(F9:F16) -> 2 | G17: =SUM(G9:G16) -> 59 | H17: =AVERAGEIFS(Riesgos!$M$4:$M$89,Riesgos!$B$4:$B$89,"Brecha") -> 8.4745763 | I17: =_xlfn.MAXIFS(Riesgos!$M$4:$M$89,Riesgos!$B$4:$B$89,"Brecha") -> 20 | L17: Prioridad | M17: Acciones | O17: Fase | P17: RM | Q17: Plazo
L18: Crítica | M18: =COUNTIF('Plan de Acción'!$D$4:$D$34,L18) -> 7 | O18: Fase 1 | P18: =COUNTIFS(Riesgos!$N$4:$N$89,O18,Riesgos!$K$4:$K$89,"Hoja de ruta Acuerdo 07-2025") -> 7 | Q18: 0–30 días
B19: DISTRIBUCIÓN DE BRECHAS POR NIVEL | L19: Alta | M19: =COUNTIF('Plan de Acción'!$D$4:$D$34,L19) -> 14 | O19: Fase 2 | P19: =COUNTIFS(Riesgos!$N$4:$N$89,O19,Riesgos!$K$4:$K$89,"Hoja de ruta Acuerdo 07-2025") -> 13 | Q19: 30–120 días
B20: Nivel | C20: Brechas | L20: Media | M20: =COUNTIF('Plan de Acción'!$D$4:$D$34,L20) -> 10 | O20: Fase 3 | P20: =COUNTIFS(Riesgos!$N$4:$N$89,O20,Riesgos!$K$4:$K$89,"Hoja de ruta Acuerdo 07-2025") -> 4 | Q20: > 120 días
B21: CRÍTICO | C21: =COUNTIF(Riesgos!$J$4:$J$89,B21) -> 8 | L21: Total | M21: =SUM(M18:M20) -> 31 | O21: Total | P21: =SUM(P18:P20) -> 24
B22: MEDIO-ALTO | C22: =COUNTIF(Riesgos!$J$4:$J$89,B22) -> 22
B23: MEDIO | C23: =COUNTIF(Riesgos!$J$4:$J$89,B23) -> 27
B24: BAJO | C24: =COUNTIF(Riesgos!$J$4:$J$89,B24) -> 2
B25: % Crítico + Medio-Alto | C25: =IFERROR((C21+C22)/SUM(C21:C24),0) -> 0.50847458
B35: BRECHAS CRÍTICAS (ordenadas por puntaje P×I) – acción inmediata 0-30 días
B36: ID · Brecha | G36: Componente | H36: P:I | I36: Puntaje P×I | J36: Plan de acción
B37: {=_xlfn.LET(_xlpm.f,Riesgos!$J$4:$J$89="CRÍTICO",_xlpm.s,_xlfn._xlws.FILTER(Riesgos!$M$4:$M$89,_xlpm.f),_xlpm.a,_xlfn._xlws.FILTER(Riesgos!$A$4:$A$89,_xlpm.f),_xlfn.SORTBY(LEFT(_xlpm.a,FIND(". ",_xlpm.a)-1),_xlpm.s,-1))} -> DD-01 · Observaciones en el 88.24 % de los expedientes de clientes | G37: {=_xlfn.LET(_xlpm.f,Riesgos!$J$4:$J$89="CRÍTICO",_xlpm.s,_xlfn._xlws.FILTER(Riesgos!$M$4:$M$89,_xlpm.f),_xlfn.SORTBY(_xlfn._xlws.FILTER(Riesgos!$K$4:$K$89,_xlpm.f),_xlpm.s,-1))} -> Debida Diligencia | H37: {=_xlfn.LET(_xlpm.f,Riesgos!$J$4:$J$89="CRÍTICO",_xlpm.s,_xlfn._xlws.FILTER(Riesgos!$M$4:$M$89,_xlpm.f),_xlfn.SORTBY(_xlfn._xlws.FILTER(Riesgos!$I$4:$I$89,_xlpm.f),_xlpm.s,-1))} -> 5:4 | I37: {=_xlfn.LET(_xlpm.f,Riesgos!$J$4:$J$89="CRÍTICO",_xlpm.s,_xlfn._xlws.FILTER(Riesgos!$M$4:$M$89,_xlpm.f),_xlfn.SORTBY(_xlpm.s,_xlpm.s,-1))} -> 20 | J37: {=_xlfn.LET(_xlpm.f,Riesgos!$J$4:$J$89="CRÍTICO",_xlpm.s,_xlfn._xlws.FILTER(Riesgos!$M$4:$M$89,_xlpm.f),_xlfn.SORTBY(_xlfn._xlws.FILTER(Riesgos!$N$4:$N$89,_xlpm.f),_xlpm.s,-1))} -> PA-07
B38: GC-01 · Oficial de Cumplimiento con doble función y sin apoyo profesional | G38: Gobierno Corporativo | H38: 4:4 | I38: 16 | J38: PA-01
B39: MT-01 · Monitoreo transaccional manual sin cronograma de automatización | G39: Monitoreo Transaccional | H39: 4:4 | I39: 16 | J39: PA-13
B40: DD-02 · Emisión sin perfil de riesgo y canal web con CTC incompleto | G40: Debida Diligencia | H40: 4:4 | I40: 16 | J40: PA-05
B41: ER-01 · Matrices BC/FT/FPADM sin copia aportada y sin evaluación institucional integrada | G41: Evaluación de Riesgo AML | H41: 4:4 | I41: 16 | J41: PA-09
B42: RR-01 · Sin ROS en el período ni registro de operaciones inusuales | G42: Reportes Regulatorios | H42: 4:4 | I42: 16 | J42: PA-04
B43: DD-08 · Conoce a tu Colaborador desactualizado | G43: Debida Diligencia | H43: 5:3 | I43: 15 | J43: PA-08
B44: RR-02 · Caso de Fianzas 2024 no escalado a Cumplimiento | G44: Reportes Regulatorios | H44: 3:5 | I44: 15 | J44: PA-03

Sheet Variables
A1: ASEGURADORA ANCÓN, S.A. – VARIABLES DE VALORACIÓN DE RIESGOS BC/FT/FPADM
A2: Evaluación Independiente 2024-2025 | Preparado por: José A. Serrano | Octubre de 2026
A4: ESCALA DE PROBABILIDAD
A5: Nombre | B5: Descripción | E5: Puntaje
A6: Frecuente | B6: La probabilidad de ocurrencia del riesgo es muy alta; sucede en la mayoría de las circunstancias. | E6: 5
A7: Probable | B7: Es probable que el riesgo ocurra; los controles o procesos no son suficientemente efectivos para prevenirlo. | E7: 4
A8: Ocasional | B8: Existe la posibilidad de que el riesgo ocurra; los controles de mitigación no son del todo efectivos. | E8: 3
A9: Posible | B9: Existe una posibilidad limitada de que el riesgo ocurra; es poco probable con los controles actuales. | E9: 2
A10: Improbable | B10: La probabilidad de materialización es extremadamente baja; los controles son altamente efectivos. | E10: 1
A12: ESCALA DE IMPACTO
A13: Nombre | B13: Descripción | E13: Puntaje
A14: Catastrófico | B14: La materialización causaría impacto severo e irreversible: sanciones regulatorias mayores, pérdidas masivas, daño reputacional crítico. | E14: 5
A15: Mayor | B15: Generaría pérdidas o sanciones significativas, requiriendo intervención inmediata de la alta gerencia y la Junta Directiva. | E15: 4
A16: Moderado | B16: Impacto considerable: puede afectar operaciones o comprometer el cumplimiento regulatorio de forma parcial. | E16: 3
A17: Menor | B17: Impacto leve; genera correcciones administrativas menores sin afectar operaciones críticas. | E17: 2
A18: Insignificante | B18: Impacto mínimo sobre la operación; se resuelve con controles normales sin mayor afectación. | E18: 1
A20: TABLA DE NIVELES DE RIESGO (P × I)
A21: CLAVE (PROB:IMP) | B21: NIVEL DE RIESGO | C21: PUNTAJE P×I
A22: 5:1 | B22: MEDIO | C22: 5
A23: 5:2 | B23: MEDIO-ALTO | C23: 10
A24: 5:3 | B24: CRÍTICO | C24: 15
A25: 5:4 | B25: CRÍTICO | C25: 20
A26: 5:5 | B26: CRÍTICO | C26: 25
A27: 4:1 | B27: MEDIO | C27: 4
A28: 4:2 | B28: MEDIO-ALTO | C28: 8
A29: 4:3 | B29: MEDIO-ALTO | C29: 12
A30: 4:4 | B30: CRÍTICO | C30: 16
A31: 4:5 | B31: CRÍTICO | C31: 20
A32: 3:1 | B32: BAJO | C32: 3
A33: 3:2 | B33: MEDIO | C33: 6
... A46: 1:5 | B46: MEDIO | C46: 5
A47: OM | B47: OPT. DE MEJORA | C47: N/A
A49: DESCRIPCIÓN DE NIVELES DE RIESGO
A50: Nivel | B50: Descripción / Acción Requerida | E50: Puntaje P×I
A51: BAJO | B51: Riesgo aceptable. Controles mínimos son suficientes. Monitoreo semestral. | E51: 1 – 3
A52: MEDIO | B52: Riesgo manejable. Requiere medidas correctivas (60-90 días). Monitoreo trimestral. | E52: 4 – 6
A53: MEDIO-ALTO | B53: Riesgo significativo. Requiere plan de acción formal (30-60 días). Monitoreo mensual. | E53: 8 – 12
A54: CRÍTICO | B54: Riesgo inaceptable. Acción inmediata (0-30 días). Reporte obligatorio a JD y Oficial de Cumplimiento. | E54: 15 – 25
A55: OPT. DE MEJORA | B55: No es hallazgo de incumplimiento. Mejora preventiva o de adecuación normativa prospectiva. | E55: N/A

Sheet Riesgos
A1: ASEGURADORA ANCÓN, S.A. – MATRIZ DE RIESGO GSM – EVALUACIÓN INDEPENDIENTE 2024-2025
A2: Período: 1 julio 2024 – 30 junio 2025 | Elaborado: José A. Serrano | Octubre de 2026
A3: DESCRIPCIÓN DEL HALLAZGO / OPORTUNIDAD DE MEJORA | B3: TIPO | C3: DOCUMENTO(S) AFECTADO(S) | D3: OBSERVACIÓN / NOTA GSM (actualizada oct-2026) | E3: PROBABILIDAD | F3: PROB. PUNT. | G3: IMPACTO | H3: IMP. PUNT. | I3: CALIFIC. P:I | J3: NIVEL DE RIESGO | K3: COMPONENTE | L3: BASE NORMATIVA / REFERENCIA | M3: PUNTAJE P×I | N3: PLAN DE ACCIÓN / FASE | O3: ACCIÓN REQUERIDA SEGÚN NIVEL
A4: GC-01 · Oficial de Cumplimiento con doble función y sin apoyo profesional. La Oficial de Cumplimiento también dirige el área Legal, rol en el que reporta al Gerente General, lo que limita su dedicación a la función y puede afectar su independencia. El Departamento cuenta con una asistente de apoyo administrativo, pero no con personal profesional para monitoreo, debida diligencia ni gestión de alertas. La SSRP señaló esta situación en la inspección DSR-0924-2023 y su atención sigue pendiente. | B4: Brecha | C4: Organigramas sep-2025; Resolución OAL-362; hojas de vida del Departamento; Informe SSRP DSR-0924-2023 | D4: Validado: la asistente administrativa no resuelve la dedicación exclusiva ni la falta de apoyo profesional. | E4: Probable | F4: =IFERROR(VLOOKUP(E4,Variables!$A$6:$E$10,5,0),"") -> 4 | G4: Mayor | H4: =IFERROR(VLOOKUP(G4,Variables!$A$14:$E$18,5,0),"") -> 4 | I4: =IF(B4="Oportunidad de Mejora","OM",IFERROR(CONCATENATE(F4,":",H4),"")) -> 4:4 | J4: =IFERROR(VLOOKUP(I4,Variables!$A$22:$B$47,2,FALSE()),"Por definir") -> CRÍTICO | K4: Gobierno Corporativo | L4: Acuerdo 03-2022, Arts. 5, 7 (num. 11), 8, 10 (párr. final) y 62 (num. 9, lit. b) | M4: =IF(I4="OM","N/A",IFERROR(F4*H4,"")) -> 16 | N4: PA-01 | O4: =IFERROR(VLOOKUP(J4,Variables!$A$51:$B$55,2,FALSE()),"") -> Riesgo inaceptable. Acción inmediata (0-30 días). Reporte obligatorio a JD y Oficial de Cumplimiento.
A5: GC-02 · Sin estudio de capacidad del Departamento de Cumplimiento. No existe un estudio que demuestre que los recursos humanos y tecnológicos de Cumplimiento son suficientes para el volumen de clientes, alertas y debidas diligencias de la aseguradora. | B5: Brecha | C5: Organigrama del Departamento de Cumplimiento | D5: Descripción de puesto pendiente de entrega; no se cuenta con análisis de capacidad. | E5: Ocasional | F5: =IFERROR(VLOOKUP(E5,Variables!$A$6:$E$10,5,0),"") -> 3 | G5: Moderado | H5: =IFERROR(VLOOKUP(G5,Variables!$A$14:$E$18,5,0),"") -> 3 | I5: =IF(B5="Oportunidad de Mejora","OM",IFERROR(CONCATENATE(F5,":",H5),"")) -> 3:3 | J5: =IFERROR(VLOOKUP(I5,Variables!$A$22:$B$47,2,FALSE()),"Por definir") -> MEDIO-ALTO | K5: Gobierno Corporativo | L5: Acuerdo 03-2022, Arts. 5 y 62 (num. 9, lit. d) | M5: =IF(I5="OM","N/A",IFERROR(F5*H5,"")) -> 9 | N5: PA-25 | O5: =IFERROR(VLOOKUP(J5,Variables!$A$51:$B$55,2,FALSE()),"") -> Riesgo significativo. Requiere plan de acción formal (30-60 días). Monitoreo mensual.
A6: GC-03 · Comité sin calendario ni temario y actas de seguimiento de 2024 no aportadas. El Reglamento permitía sesionar con dos de seis integrantes, incluso sin directores. La convocatoria y la agenda dependían de la Oficial de Cumplimiento, a quien el Comité supervisa, y no existían calendario anual ni temario mínimo. Ancón indica que entre la sesión del 17 de abril de 2024 y la del 28 de mayo de 2025 hubo sesiones de seguimiento sin nuevas aprobaciones, pero sus actas no han sido aportadas, de modo que el mínimo de dos sesiones anuales que el Reglamento fijaba para 2024 no puede verificarse documentalmente. | B6: Brecha | C6: AA_GOBCORP03; actas 17-04-2024 y 28-05-2025; Cuadro de Trazabilidad | D6: Actas II a IV trimestre 2024 pendientes de entrega (sesiones de seguimiento según la aclaración). Ancón indicó que no existen calendario ni temario. | E6: Probable | F6: =IFERROR(VLOOKUP(E6,Variables!$A$6:$E$10,5,0),"") -> 4 | G6: Moderado | H6: =IFERROR(VLOOKUP(G6,Variables!$A$14:$E$18,5,0),"") -> 3 | I6: =IF(B6="Oportunidad de Mejora","OM",IFERROR(CONCATENATE(F6,":",H6),"")) -> 4:3 | J6: =IFERROR(VLOOKUP(I6,Variables!$A$22:$B$47,2,FALSE()),"Por definir") -> MEDIO-ALTO | K6: Gobierno Corporativo | L6: Reglamento AA_GOBCORP03; Acuerdo 03-2022, Arts. 10 (num. 14) y 11 | M6: =IF(I6="OM","N/A",IFERROR(F6*H6,"")) -> 12 | N6: PA-12 | O6: =IFERROR(VLOOKUP(J6,Variables!$A$51:$B$55,2,FALSE()),"") -> Riesgo significativo. Requiere plan de acción formal (30-60 días). Monitoreo mensual.
A7: GC-04 · Sin informes del Comité a la Junta y autoevaluación sin soporte. El Reglamento no definía periodicidad, formato ni contenido del reporte del Comité a la Junta; no se aportaron informes a la Junta, y Ancón indicó que no existe un informe anual de gestión del Comité. Tampoco se evaluó el desempeño del Comité en 2024 ni en 2025; esto se atendió después, con la actualización al Acuerdo 3-2025. La autoevaluación de octubre de 2025 es un buen comienzo, pero sus 19 respuestas afirmativas no tienen soporte, la hoja de resumen marca 0 % por un error de fórmulas, no evalúa el funcionamiento, la composición del Comité ni la calidad de la información que recibe, y no está firmada ni fue presentada a la Junta. | B7: Brecha | C7: AA_GOBCORP03; autoevaluación del Comité 01-10-2025 | D7: Informes a Junta y memorandos a Gerencia pendientes de entrega. | E7: Ocasional | F7: =IFERROR(VLOOKUP(E7,Variables!$A$6:$E$10,5,0),"") -> 3 | G7: Moderado | H7: =IFERROR(VLOOKUP(G7,Variables!$A$14:$E$18,5,0),"") -> 3 | I7: =IF(B7="Oportunidad de Mejora","OM",IFERROR(CONCATENATE(F7,":",H7),"")) -> 3:3 | J7: =IFERROR(VLOOKUP(I7,Variables!$A$22:$B$47,2,FALSE()),"Por definir") -> MEDIO-ALTO | K7: Gobierno Corporativo | L7: Acuerdo 03-2022, Art. 10 (nums. 14 y 15) | M7: =IF(I7="OM","N/A",IFERROR(F7*H7,"")) -> 9 | N7: PA-12, PA-26 | O7: =IFERROR(VLOOKUP(J7,Variables!$A$51:$B$55,2,FALSE()),"") -> Riesgo significativo. Requiere plan de acción formal (30-60 días). Monitoreo mensual.
A8: GC-05 · Código de Ética incompleto y sin política de partes relacionadas. El Código de Ética (AIN-28-CODETI, noviembre de 2023) existe, pero no incluye un procedimiento para declarar y gestionar conflictos de interés, reglas para operaciones con partes vinculadas, un canal de denuncia confidencial con protección frente a represalias, un responsable de seguimiento ni consecuencias por incumplimiento; además, lo elaboró Auditoría Interna, que luego debe evaluarlo. Ancón indicó que no tiene una política de transacciones con partes relacionadas, y en las entrevistas el personal no identificó un canal de denuncia anónimo. | B8: Brecha | C8: AIN-28-CODETI; entrevistas | D8: Política de partes relacionadas: Ancón indicó que no existe. | E8: Ocasional | F8: =IFERROR(VLOOKUP(E8,Variables!$A$6:$E$10,5,0),"") -> 3 | G8: Moderado | H8: =IFERROR(VLOOKUP(G8,Variables!$A$14:$E$18,5,0),"") -> 3 | I8: =IF(B8="Oportunidad de Mejora","OM",IFERROR(CONCATENATE(F8,":",H8),"")) -> 3:3 | J8: =IFERROR(VLOOKUP(I8,Variables!$A$22:$B$47,2,FALSE()),"Por definir") -> MEDIO-ALTO | K8: Gobierno Corporativo | L8: Manual del Sistema de Control Interno, secc. 6.1; Ley 23 de 2015, Art. 57; Acuerdo 03-2022, Art. 15 (num. 8); Recomendación 18 del GAFI | M8: =IF(I8="OM","N/A",IFERROR(F8*H8,"")) -> 9 | N8: PA-18 | O8: =IFERROR(VLOOKUP(J8,Variables!$A$51:$B$55,2,FALSE()),"") -> Riesgo significativo. Requiere plan de acción formal (30-60 días). Monitoreo mensual.
A9: GC-06 · Debilidades de trazabilidad en documentos de gobierno. El acta de Junta del 20-01-2021 aprueba un reglamento sin identificar código ni versión, no muestra firmas y cita un "Acuerdo 22" que no corresponde; la lista de integrantes del Comité no está al día; el Manual del Sistema de Control Interno V2.0 (2024) solo cambió el formato de la versión de 2020 y aún remite a normas de la Superintendencia Financiera de Colombia; y el Manual de RR.HH. no indica quién lo aprobó. | B9: Brecha | C9: Acta JD 20-01-2021; AA_GOBCORP03; AIN-28-MSCI-1; GESREHU-1 | D9: Revisado. | E9: Ocasional | F9: =IFERROR(VLOOKUP(E9,Variables!$A$6:$E$10,5,0),"") -> 3 | G9: Menor | H9: =IFERROR(VLOOKUP(G9,Variables!$A$14:$E$18,5,0),"") -> 2 | I9: =IF(B9="Oportunidad de Mejora","OM",IFERROR(CONCATENATE(F9,":",H9),"")) -> 3:2 | J9: =IFERROR(VLOOKUP(I9,Variables!$A$22:$B$47,2,FALSE()),"Por definir") -> MEDIO | K9: Gobierno Corporativo | L9: Manual del Sistema de Control Interno, secc. 6.1; Acuerdo 03-2022, Arts. 11 y 14 | M9: =IF(I9="OM","N/A",IFERROR(F9*H9,"")) -> 6 | N9: PA-22 | O9: =IFERROR(VLOOKUP(J9,Variables!$A$51:$B$55,2,FALSE()),"") -> Riesgo manejable. Requiere medidas correctivas (60-90 días). Monitoreo trimestral.
A10: GC-07 · Planificación de Auditoría Interna sin enfoque de riesgo explícito. Los Planes de Auditoría Interna 2024 y 2025 no muestran una planificación basada en riesgos ni los elementos formales de aprobación, alcance, recursos y reprogramación de trabajos no ejecutados, y el Plan 2025 no incluye la revisión del área de Cumplimiento. Como aspecto positivo, Ancón aportó un informe anual de Auditoría Interna al Departamento de Cumplimiento; recomendamos que la revisión de Cumplimiento quede programada de forma expresa en cada plan anual. | B10: Brecha | C10: Planes de Auditoría Interna 2024 y 2025; Informe de Auditoría Interna al Dpto. de Cumplimiento | D10: Informe de Auditoría Interna al Dpto. de Cumplimiento aportado. | E10: Posible | F10: =IFERROR(VLOOKUP(E10,Variables!$A$6:$E$10,5,0),"") -> 2 | G10: Moderado | H10: =IFERROR(VLOOKUP(G10,Variables!$A$14:$E$18,5,0),"") -> 3 | I10: =IF(B10="Oportunidad de Mejora","OM",IFERROR(CONCATENATE(F10,":",H10),"")) -> 2:3 | J10: =IFERROR(VLOOKUP(I10,Variables!$A$22:$B$47,2,FALSE()),"Por definir") -> MEDIO | K10: Gobierno Corporativo | L10: Ley 23 de 2015, Art. 45; Acuerdo 03-2022, Art. 18 | M10: =IF(I10="OM","N/A",IFERROR(F10*H10,"")) -> 6 | N10: PA-21 | O10: =IFERROR(VLOOKUP(J10,Variables!$A$51:$B$55,2,FALSE()),"") -> Riesgo manejable. Requiere medidas correctivas (60-90 días). Monitoreo trimestral.
A11: GC-08 · Sin suplente ni continuidad de la función de prevención. No hay un suplente designado ni un plan que asegure la continuidad de la función de prevención si la Oficial de Cumplimiento se ausenta. | B11: Brecha | C11: Organigrama; Manual de Prevención | D11: No evidenciado. | E11: Posible | F11: =IFERROR(VLOOKUP(E11,Variables!$A$6:$E$10,5,0),"") -> 2 | G11: Moderado | H11: =IFERROR(VLOOKUP(G11,Variables!$A$14:$E$18,5,0),"") -> 3 | I11: =IF(B11="Oportunidad de Mejora","OM",IFERROR(CONCATENATE(F11,":",H11),"")) -> 2:3 | J11: =IFERROR(VLOOKUP(I11,Variables!$A$22:$B$47,2,FALSE()),"Por definir") -> MEDIO | K11: Gobierno Corporativo | L11: Acuerdo 03-2022, Art. 9 | M11: =IF(I11="OM","N/A",IFERROR(F11*H11,"")) -> 6 | N11: PA-27 | O11: =IFERROR(VLOOKUP(J11,Variables!$A$51:$B$55,2,FALSE()),"") -> Riesgo manejable. Requiere medidas correctivas (60-90 días). Monitoreo trimestral.
A12: GC-09 · Vacantes en funciones que sostienen el modelo de prevención. Están vacantes o concentradas las posiciones de Oficial de Protección de Datos, Gerencia de Recursos Humanos y una gerencia propia para Emisión, que hoy reporta a la Gerencia General. La designación del Oficial de Protección de Datos se planteó en comité, pero sigue sin resolverse. | B12: Brecha | C12: Organigrama general; entrevistas | D12: Confirmado en entrevistas. | E12: Ocasional | F12: =IFERROR(VLOOKUP(E12,Variables!$A$6:$E$10,5,0),"") -> 3 | G12: Menor | H12: =IFERROR(VLOOKUP(G12,Variables!$A$14:$E$18,5,0),"") -> 2 | I12: =IF(B12="Oportunidad de Mejora","OM",IFERROR(CONCATENATE(F12,":",H12),"")) -> 3:2 | J12: =IFERROR(VLOOKUP(I12,Variables!$A$22:$B$47,2,FALSE()),"Por definir") -> MEDIO | K12: Gobierno Corporativo | L12: Ley 81 de 2019; Acuerdo 03-2022, Art. 16 | M12: =IF(I12="OM","N/A",IFERROR(F12*H12,"")) -> 6 | N12: PA-27 | O12: =IFERROR(VLOOKUP(J12,Variables!$A$51:$B$55,2,FALSE()),"") -> Riesgo manejable. Requiere medidas correctivas (60-90 días). Monitoreo trimestral.
A13: GC-10 · Designación del Oficial sin acta de Junta ni descripción de puesto. Para la designación de la Oficial de Cumplimiento se cuenta con la Resolución OAL-362 de 30 de diciembre de 2022; el acta de Junta Directiva que la designa y la descripción del puesto están pendientes de entrega. | B13: Brecha | C13: Resolución OAL-362 | D13: Acta de Junta y descripción de puesto pendientes de entrega. | E13: Posible | F13: =IFERROR(VLOOKUP(E13,Variables!$A$6:$E$10,5,0),"") -> 2 | G13: Moderado | H13: =IFERROR(VLOOKUP(G13,Variables!$A$14:$E$18,5,0),"") -> 3 | I13: =IF(B13="Oportunidad de Mejora","OM",IFERROR(CONCATENATE(F13,":",H13),"")) -> 2:3 | J13: =IFERROR(VLOOKUP(I13,Variables!$A$22:$B$47,2,FALSE()),"Por definir") -> MEDIO | K13: Gobierno Corporativo | L13: Acuerdo 03-2022, Arts. 5 y 8 | M13: =IF(I13="OM","N/A",IFERROR(F13*H13,"")) -> 6 | N13: PA-01 | O13: =IFERROR(VLOOKUP(J13,Variables!$A$51:$B$55,2,FALSE()),"") -> Riesgo manejable. Requiere medidas correctivas (60-90 días). Monitoreo trimestral.
A14: GC-11 · Ratificación de la Junta Directiva sin evidencia concluyente. La aclaración de Ancón documenta las aprobaciones del Comité, pero la ratificación por la Junta Directiva del Manual de Prevención, de la matriz de riesgo y de la herramienta de listas no está evidenciada, y las actas de Junta aportadas sobre los Programas 2024 y 2025 y el Informe de Gestión 2024 están sujetas a confirmación con la Oficial de Cumplimiento. | B14: Brecha | C14: Aclaración de aprobaciones del Comité; actas de Junta aportadas | D14: Actas de Junta del Manual, la matriz y la herramienta de listas pendientes de entrega; las demás, sujetas a confirmación. | E14: Ocasional | F14: =IFERROR(VLOOKUP(E14,Variables!$A$6:$E$10,5,0),"") -> 3 | G14: Moderado | H14: =IFERROR(VLOOKUP(G14,Variables!$A$14:$E$18,5,0),"") -> 3 | I14: =IF(B14="Oportunidad de Mejora","OM",IFERROR(CONCATENATE(F14,":",H14),"")) -> 3:3 | J14: =IFERROR(VLOOKUP(I14,Variables!$A$22:$B$47,2,FALSE()),"Por definir") -> MEDIO-ALTO | K14: Gobierno Corporativo | L14: Acuerdo 03-2022, Arts. 11, 12, 13, 14 y 15 (aprobación del Comité y ratificación de la Junta) | M14: =IF(I14="OM","N/A",IFERROR(F14*H14,"")) -> 9 | N14: PA-10 | O14: =IFERROR(VLOOKUP(J14,Variables!$A$51:$B$55,2,FALSE()),"") -> Riesgo significativo. Requiere plan de acción formal (30-60 días). Monitoreo mensual.
A15: PP-01 · Manual describe la consulta en listas solo para alto riesgo. El Manual describe la consulta en listas OFAC y ONU solo para clientes de alto riesgo, aspecto que la SSRP observó en 2022. En la práctica, Ancón aportó evidencia de la herramienta de consulta, de barridos sobre la cartera existente y de pólizas rechazadas o canceladas por coincidencias, por lo que la brecha es principalmente documental: el Manual debe reflejar que el control se aplica a todos. | B15: Brecha | C15: MPREMET-21; CONCLI-15; herramienta de listas; constancia de barridos | D15: Validado con evidencia de barridos del período: el control opera; falta alinear el texto del Manual. | E15: Posible | F15: =IFERROR(VLOOKUP(E15,Variables!$A$6:$E$10,5,0),"") -> 2 | G15: Moderado | H15: =IFERROR(VLOOKUP(G15,Variables!$A$14:$E$18,5,0),"") -> 3 | I15: =IF(B15="Oportunidad de Mejora","OM",IFERROR(CONCATENATE(F15,":",H15),"")) -> 2:3 | J15: =IFERROR(VLOOKUP(I15,Variables!$A$22:$B$47,2,FALSE()),"Por definir") -> MEDIO | K15: Políticas y Procedimientos | L15: Ley 23 de 2015, Art. 49; Acuerdo 03-2022, Arts. 21 (num. 2) y 23 (num. 9) | M15: =IF(I15="OM","N/A",IFERROR(F15*H15,"")) -> 6 | N15: PA-06 | O15: =IFERROR(VLOOKUP(J15,Variables!$A$51:$B$55,2,FALSE()),"") -> Riesgo manejable. Requiere medidas correctivas (60-90 días). Monitoreo trimestral.
... A89: RM-24 · Planes de actualización de expedientes (Art. 7, lits. f y g). Formalizar ambos planes con metas trimestrales y reportarlos en el informe trimestral. | B89: Oportunidad de Mejora | C89: PAC / DD | D89: Qué cambia: Planes de actualización de clientes con operaciones inconsistentes y de colaboradores, con informe a Comité y Junta. Situación en Ancón: Expedientes de colaboradores desactualizados (DD-08). | E89: Posible | F89: =IFERROR(VLOOKUP(E89,Variables!$A$6:$E$10,5,0),"") -> 2 | G89: Moderado | H89: =IFERROR(VLOOKUP(G89,Variables!$A$14:$E$18,5,0),"") -> 3 | I89: =IF(B89="Oportunidad de Mejora","OM",IFERROR(CONCATENATE(F89,":",H89),"")) -> OM | J89: =IFERROR(VLOOKUP(I89,Variables!$A$22:$B$47,2,FALSE()),"Por definir") -> OPT. DE MEJORA | K89: Hoja de ruta Acuerdo 07-2025 | L89: Acuerdo SSRP 07-2025 (fuera del alcance; valor agregado) | M89: =IF(I89="OM","N/A",IFERROR(F89*H89,"")) -> N/A | N89: Fase 2 | O89: =IFERROR(VLOOKUP(J89,Variables!$A$51:$B$55,2,FALSE()),"") -> No es hallazgo de incumplimiento. Mejora preventiva o de adecuación normativa prospectiva.

Sheet Matriz de Riesgos
A1: MAPA DE RIESGO – ASEGURADORA ANCÓN, S.A. (Probabilidad × Impacto)
A2: Los valores de cada celda son generados automáticamente desde la hoja Riesgos | COUNTIF(Riesgos!$I$4:$I$120) | Evaluación Independiente 2024-2025
A3: PROBABILIDAD ↓ / IMPACTO → | C3: 1 Insignificante | D3: 2 Menor | E3: 3 Moderado | F3: 4 Mayor | G3: 5 Catastrófico
A4: 5 Frecuente | B4: 5 | C4: =COUNTIF(Riesgos!$I$4:$I$120,"5:1") -> 0 | D4: =COUNTIF(Riesgos!$I$4:$I$120,"5:2") -> 0 | E4: =COUNTIF(Riesgos!$I$4:$I$120,"5:3") -> 1 | F4: =COUNTIF(Riesgos!$I$4:$I$120,"5:4") -> 1 | G4: =COUNTIF(Riesgos!$I$4:$I$120,"5:5") -> 0
A5: 4 Probable | B5: 4 | C5: =COUNTIF(Riesgos!$I$4:$I$120,"4:1") -> 0 | D5: =COUNTIF(Riesgos!$I$4:$I$120,"4:2") -> 0 | E5: =COUNTIF(Riesgos!$I$4:$I$120,"4:3") -> 6 | F5: =COUNTIF(Riesgos!$I$4:$I$120,"4:4") -> 5 | G5: =COUNTIF(Riesgos!$I$4:$I$120,"4:5") -> 0
A6: 3 Ocasional | B6: 3 | C6: =COUNTIF(Riesgos!$I$4:$I$120,"3:1") -> 0 | D6: =COUNTIF(Riesgos!$I$4:$I$120,"3:2") -> 11 | E6: =COUNTIF(Riesgos!$I$4:$I$120,"3:3") -> 14 | F6: =COUNTIF(Riesgos!$I$4:$I$120,"3:4") -> 1 | G6: =COUNTIF(Riesgos!$I$4:$I$120,"3:5") -> 1
A7: 2 Posible | B7: 2 | C7: =COUNTIF(Riesgos!$I$4:$I$120,"2:1") -> 1 | D7: =COUNTIF(Riesgos!$I$4:$I$120,"2:2") -> 7 | E7: =COUNTIF(Riesgos!$I$4:$I$120,"2:3") -> 9 | F7: =COUNTIF(Riesgos!$I$4:$I$120,"2:4") -> 1 | G7: =COUNTIF(Riesgos!$I$4:$I$120,"2:5") -> 0
A8: 1 Improbable | B8: 1 | C8: =COUNTIF(Riesgos!$I$4:$I$120,"1:1") -> 0 | D8: =COUNTIF(Riesgos!$I$4:$I$120,"1:2") -> 1 | E8: =COUNTIF(Riesgos!$I$4:$I$120,"1:3") -> 0 | F8: =COUNTIF(Riesgos!$I$4:$I$120,"1:4") -> 0 | G8: =COUNTIF(Riesgos!$I$4:$I$120,"1:5") -> 0
B9: Score | C9: 1 | D9: 2 | E9: 3 | F9: 4 | G9: 5
A11: LEYENDA DE NIVELES DE RIESGO
A12: CRÍTICO | B12: P×I ≥ 15 | C12: Acción inmediata (0-30 días). Reporte obligatorio a Junta Directiva y Oficial de Cumplimiento.
A13: MEDIO-ALTO | B13: P×I 8-12 | C13: Plan de acción formal (30-60 días). Monitoreo mensual.
A14: MEDIO | B14: P×I 4-6 | C14: Medidas correctivas (60-90 días). Monitoreo trimestral.
A15: BAJO | B15: P×I 1-3 | C15: Riesgo aceptable con controles mínimos. Monitoreo semestral.
A16: OPT. DE MEJORA | B16: N/A | C16: No es hallazgo de incumplimiento. Mejora preventiva o adecuación normativa prospectiva.
A18: RESUMEN – BRECHAS Y OPORTUNIDADES DE MEJORA (Período: julio 2024 – junio 2025)
A19: Brechas CRÍTICAS | G19: =COUNTIF(Riesgos!$J$4:$J$120,"CRÍTICO") -> 8
A20: Brechas MEDIO-ALTO | G20: =COUNTIF(Riesgos!$J$4:$J$120,"MEDIO-ALTO") -> 22
A21: Brechas MEDIAS | G21: =COUNTIF(Riesgos!$J$4:$J$120,"MEDIO") -> 27
A22: Brechas BAJAS | G22: =COUNTIF(Riesgos!$J$4:$J$120,"BAJO") -> 2
A23: Oportunidades de Mejora | G23: =COUNTIF(Riesgos!$J$4:$J$120,"OPT. DE MEJORA") -> 27
A24: TOTAL HALLAZGOS (Brechas) | G24: =COUNTIF(Riesgos!$B$4:$B$120,"Brecha") -> 59
A25: TOTAL REGISTROS EN MATRIZ | G25: =COUNTA(Riesgos!$A$4:$A$120) -> 86
A27: RESUMEN POR COMPONENTE – BRECHAS DEL PERÍODO (julio 2024 – junio 2025)
A28: Componente | D28: CRÍTICO | E28: MEDIO-ALTO | F28: MEDIO | G28: BAJO | H28: TOTAL
A29: Gobierno Corporativo | D29: =COUNTIFS(Riesgos!$K$4:$K$120,$A29,Riesgos!$J$4:$J$120,"CRÍTICO") -> 1 | E29: =COUNTIFS(Riesgos!$K$4:$K$120,$A29,Riesgos!$J$4:$J$120,"MEDIO-ALTO") -> 5 | F29: =COUNTIFS(Riesgos!$K$4:$K$120,$A29,Riesgos!$J$4:$J$120,"MEDIO") -> 5 | G29: =COUNTIFS(Riesgos!$K$4:$K$120,$A29,Riesgos!$J$4:$J$120,"BAJO") -> 0 | H29: =SUM(D29:G29) -> 11
A30: Políticas y Procedimientos | D30: =COUNTIFS(Riesgos!$K$4:$K$120,$A30,Riesgos!$J$4:$J$120,"CRÍTICO") -> 0 | E30: =COUNTIFS(Riesgos!$K$4:$K$120,$A30,Riesgos!$J$4:$J$120,"MEDIO-ALTO") -> 2 | F30: =COUNTIFS(Riesgos!$K$4:$K$120,$A30,Riesgos!$J$4:$J$120,"MEDIO") -> 7 | G30: =COUNTIFS(Riesgos!$K$4:$K$120,$A30,Riesgos!$J$4:$J$120,"BAJO") -> 1 | H30: =SUM(D30:G30) -> 10
A31: Programa Anual de Cumplimiento | D31: =COUNTIFS(Riesgos!$K$4:$K$120,$A31,Riesgos!$J$4:$J$120,"CRÍTICO") -> 0 | E31: =COUNTIFS(Riesgos!$K$4:$K$120,$A31,Riesgos!$J$4:$J$120,"MEDIO-ALTO") -> 2 | F31: =COUNTIFS(Riesgos!$K$4:$K$120,$A31,Riesgos!$J$4:$J$120,"MEDIO") -> 4 | G31: =COUNTIFS(Riesgos!$K$4:$K$120,$A31,Riesgos!$J$4:$J$120,"BAJO") -> 0 | H31: =SUM(D31:G31) -> 6
A32: Monitoreo Transaccional | D32: =COUNTIFS(Riesgos!$K$4:$K$120,$A32,Riesgos!$J$4:$J$120,"CRÍTICO") -> 1 | E32: =COUNTIFS(Riesgos!$K$4:$K$120,$A32,Riesgos!$J$4:$J$120,"MEDIO-ALTO") -> 5 | F32: =COUNTIFS(Riesgos!$K$4:$K$120,$A32,Riesgos!$J$4:$J$120,"MEDIO") -> 1 | G32: =COUNTIFS(Riesgos!$K$4:$K$120,$A32,Riesgos!$J$4:$J$120,"BAJO") -> 1 | H32: =SUM(D32:G32) -> 8
A33: Debida Diligencia | D33: =COUNTIFS(Riesgos!$K$4:$K$120,$A33,Riesgos!$J$4:$J$120,"CRÍTICO") -> 3 | E33: =COUNTIFS(Riesgos!$K$4:$K$120,$A33,Riesgos!$J$4:$J$120,"MEDIO-ALTO") -> 4 | F33: =COUNTIFS(Riesgos!$K$4:$K$120,$A33,Riesgos!$J$4:$J$120,"MEDIO") -> 1 | G33: =COUNTIFS(Riesgos!$K$4:$K$120,$A33,Riesgos!$J$4:$J$120,"BAJO") -> 0 | H33: =SUM(D33:G33) -> 8
A34: Evaluación de Riesgo AML | D34: =COUNTIFS(Riesgos!$K$4:$K$120,$A34,Riesgos!$J$4:$J$120,"CRÍTICO") -> 1 | E34: =COUNTIFS(Riesgos!$K$4:$K$120,$A34,Riesgos!$J$4:$J$120,"MEDIO-ALTO") -> 1 | F34: =COUNTIFS(Riesgos!$K$4:$K$120,$A34,Riesgos!$J$4:$J$120,"MEDIO") -> 3 | G34: =COUNTIFS(Riesgos!$K$4:$K$120,$A34,Riesgos!$J$4:$J$120,"BAJO") -> 0 | H34: =SUM(D34:G34) -> 5
A35: Reportes Regulatorios | D35: =COUNTIFS(Riesgos!$K$4:$K$120,$A35,Riesgos!$J$4:$J$120,"CRÍTICO") -> 2 | E35: =COUNTIFS(Riesgos!$K$4:$K$120,$A35,Riesgos!$J$4:$J$120,"MEDIO-ALTO") -> 2 | F35: =COUNTIFS(Riesgos!$K$4:$K$120,$A35,Riesgos!$J$4:$J$120,"MEDIO") -> 2 | G35: =COUNTIFS(Riesgos!$K$4:$K$120,$A35,Riesgos!$J$4:$J$120,"BAJO") -> 0 | H35: =SUM(D35:G35) -> 6
A36: Conservación de Documentos | D36: =COUNTIFS(Riesgos!$K$4:$K$120,$A36,Riesgos!$J$4:$J$120,"CRÍTICO") -> 0 | E36: =COUNTIFS(Riesgos!$K$4:$K$120,$A36,Riesgos!$J$4:$J$120,"MEDIO-ALTO") -> 1 | F36: =COUNTIFS(Riesgos!$K$4:$K$120,$A36,Riesgos!$J$4:$J$120,"MEDIO") -> 4 | G36: =COUNTIFS(Riesgos!$K$4:$K$120,$A36,Riesgos!$J$4:$J$120,"BAJO") -> 0 | H36: =SUM(D36:G36) -> 5
A37: TOTAL | D37: =SUM(D29:D36) -> 8 | E37: =SUM(E29:E36) -> 22 | F37: =SUM(F29:F36) -> 27 | G37: =SUM(G29:G36) -> 2 | H37: =SUM(H29:H36) -> 59
A39: Nota: las oportunidades de mejora (OM) no se califican como brechas. Las RM corresponden a la hoja de ruta hacia el Acuerdo SSRP 07-2025, que está fuera del alcance de la evaluación del período y se incluye como valor agregado.

Sheet Plan de Acción
A1: ASEGURADORA ANCÓN, S.A. – PLAN DE ACCIÓN (PA-01 a PA-31) – Informe Final PBC
A3: ID | B3: ACCIÓN | C3: COMPONENTE | D3: PRIORIDAD | E3: RESPONSABLE | F3: PLAZO | G3: EVIDENCIA | H3: REGISTROS VINCULADOS | I3: BRECHAS CRÍTICAS | J3: BRECHAS MEDIO-ALTO
A4: PA-01 | B4: Llevar a la Junta la decisión de separar las funciones de Cumplimiento y Legal, aprobar al menos un analista PBC dedicado y formalizar en acta la designación y la descripción de puesto del Oficial. | C4: GC | D4: Crítica | E4: Junta Directiva / Gerencia General | F4: 30 días | G4: Acta de Junta; perfil y requisición | H4: {=SUMPRODUCT(--ISNUMBER(SEARCH(", "&A4&",",", "&Riesgos!$N$4:$N$89&",")))} -> 2 | I4: {=SUMPRODUCT(ISNUMBER(SEARCH(", "&A4&",",", "&Riesgos!$N$4:$N$89&","))*(Riesgos!$J$4:$J$89="CRÍTICO"))} -> 1 | J4: {=SUMPRODUCT(ISNUMBER(SEARCH(", "&A4&",",", "&Riesgos!$N$4:$N$89&","))*(Riesgos!$J$4:$J$89="MEDIO-ALTO"))} -> 0
A5: PA-02 | B5: Actualizar la matriz de seguimiento del cierre de hallazgos de la inspección DSR-0924-2023 (entregada el 16-01-2026) con estado y evidencia por hallazgo; aprobarla en Comité y Junta y valorar su envío a la SSRP. | C5: RR / GC | D5: Crítica | E5: Oficial de Cumplimiento | F5: 30 días | G5: Matriz actualizada y aprobada; actas | H5: {=SUMPRODUCT(--ISNUMBER(SEARCH(", "&A5&",",", "&Riesgos!$N$4:$N$89&",")))} -> 2 | I5: {=SUMPRODUCT(ISNUMBER(SEARCH(", "&A5&",",", "&Riesgos!$N$4:$N$89&","))*(Riesgos!$J$4:$J$89="CRÍTICO"))} -> 0 | J5: {=SUMPRODUCT(ISNUMBER(SEARCH(", "&A5&",",", "&Riesgos!$N$4:$N$89&","))*(Riesgos!$J$4:$J$89="MEDIO-ALTO"))} -> 2
A6: PA-03 | B6: Analizar y documentar el caso de Fianzas 2024 y decidir sobre el ROS; enviar una circular sobre el reporte obligatorio de señales de alerta, incluidas tentativas. | C6: RR | D6: Crítica | E6: Oficial de Cumplimiento / Fianzas | F6: 15 días | G6: Expediente del caso; decisión firmada; circular | H6: {=SUMPRODUCT(--ISNUMBER(SEARCH(", "&A6&",",", "&Riesgos!$N$4:$N$89&",")))} -> 1 | I6: {=SUMPRODUCT(ISNUMBER(SEARCH(", "&A6&",",", "&Riesgos!$N$4:$N$89&","))*(Riesgos!$J$4:$J$89="CRÍTICO"))} -> 1 | J6: {=SUMPRODUCT(ISNUMBER(SEARCH(", "&A6&",",", "&Riesgos!$N$4:$N$89&","))*(Riesgos!$J$4:$J$89="MEDIO-ALTO"))} -> 0
A7: PA-04 | B7: Aprobar el procedimiento de operaciones inusuales y sospechosas con registro único, criterios de escalamiento, revisión de calidad del formato UAF y registro de decisiones de no reportar. | C7: RR | D7: Crítica | E7: Oficial de Cumplimiento / Comité | F7: 30 días | G7: Procedimiento aprobado; registro en uso | H7: {=SUMPRODUCT(--ISNUMBER(SEARCH(", "&A7&",",", "&Riesgos!$N$4:$N$89&",")))} -> 2 | I7: {=SUMPRODUCT(ISNUMBER(SEARCH(", "&A7&",",", "&Riesgos!$N$4:$N$89&","))*(Riesgos!$J$4:$J$89="CRÍTICO"))} -> 1 | J7: {=SUMPRODUCT(ISNUMBER(SEARCH(", "&A7&",",", "&Riesgos!$N$4:$N$89&","))*(Riesgos!$J$4:$J$89="MEDIO-ALTO"))} -> 1
A8: PA-05 | B8: Configurar el bloqueo de emisión sin perfil de riesgo aprobado y sin CTC completo, incluido el canal web, con aviso de perfiles por vencer. | C8: DD | D8: Crítica | E8: Tecnología / Oficial de Cumplimiento / Producción | F8: 30 días (diseño) / 60 días (producción) | G8: Pruebas y paso a producción | H8: {=SUMPRODUCT(--ISNUMBER(SEARCH(", "&A8&",",", "&Riesgos!$N$4:$N$89&",")))} -> 1 | I8: {=SUMPRODUCT(ISNUMBER(SEARCH(", "&A8&",",", "&Riesgos!$N$4:$N$89&","))*(Riesgos!$J$4:$J$89="CRÍTICO"))} -> 1 | J8: {=SUMPRODUCT(ISNUMBER(SEARCH(", "&A8&",",", "&Riesgos!$N$4:$N$89&","))*(Riesgos!$J$4:$J$89="MEDIO-ALTO"))} -> 0
A9: PA-06 | B9: Alinear el Manual con la consulta universal en listas que ya se practica; aprobar el procedimiento ante coincidencias y congelamiento preventivo; capacitar a Atención al Cliente; documentar los barridos periódicos. | C9: DD / PP | D9: Crítica | E9: Oficial de Cumplimiento / Tecnología | F9: 30 días | G9: Manual ajustado; procedimiento; asistencia; constancia de barridos | H9: {=SUMPRODUCT(--ISNUMBER(SEARCH(", "&A9&",",", "&Riesgos!$N$4:$N$89&",")))} -> 2 | I9: {=SUMPRODUCT(ISNUMBER(SEARCH(", "&A9&",",", "&Riesgos!$N$4:$N$89&","))*(Riesgos!$J$4:$J$89="CRÍTICO"))} -> 0 | J9: {=SUMPRODUCT(ISNUMBER(SEARCH(", "&A9&",",", "&Riesgos!$N$4:$N$89&","))*(Riesgos!$J$4:$J$89="MEDIO-ALTO"))} -> 1
A10: PA-07 | B10: Aprobar el plan de subsanación de los 75 expedientes observados y completar el registro de excepciones con motivo, responsable, fecha límite y escalamiento. | C10: DD / CD | D10: Alta | E10: Producción / Comercial / Oficial de Cumplimiento | F10: 30 días (plan) / 90 días (ejecución) | G10: Plan aprobado; avance quincenal | H10: {=SUMPRODUCT(--ISNUMBER(SEARCH(", "&A10&",",", "&Riesgos!$N$4:$N$89&",")))} -> 3 | I10: {=SUMPRODUCT(ISNUMBER(SEARCH(", "&A10&",",", "&Riesgos!$N$4:$N$89&","))*(Riesgos!$J$4:$J$89="CRÍTICO"))} -> 1 | J10: {=SUMPRODUCT(ISNUMBER(SEARCH(", "&A10&",",", "&Riesgos!$N$4:$N$89&","))*(Riesgos!$J$4:$J$89="MEDIO-ALTO"))} -> 2
A11: PA-08 | B11: Actualizar la Matriz de Riesgo de Colaboradores y regularizar contratos, constancias de capacitación y del Reglamento Interno. | C11: DD | D11: Alta | E11: Recursos Humanos / Oficial de Cumplimiento | F11: 60 días | G11: Matriz actualizada; expedientes completos | H11: {=SUMPRODUCT(--ISNUMBER(SEARCH(", "&A11&",",", "&Riesgos!$N$4:$N$89&",")))} -> 1 | I11: {=SUMPRODUCT(ISNUMBER(SEARCH(", "&A11&",",", "&Riesgos!$N$4:$N$89&","))*(Riesgos!$J$4:$J$89="CRÍTICO"))} -> 1 | J11: {=SUMPRODUCT(ISNUMBER(SEARCH(", "&A11&",",", "&Riesgos!$N$4:$N$89&","))*(Riesgos!$J$4:$J$89="MEDIO-ALTO"))} -> 0
A12: PA-09 | B12: Entregar las matrices aprobadas (productos, clientes, proveedores, empleados y provincias) y consolidarlas en una Evaluación Institucional de Riesgo BC/FT/FPADM aprobada en Comité y Junta. | C12: ER | D12: Crítica | E12: Oficial de Cumplimiento | F12: 30 días (metodología) / 90 días (aprobación) | G12: Metodología; matriz aprobada | H12: {=SUMPRODUCT(--ISNUMBER(SEARCH(", "&A12&",",", "&Riesgos!$N$4:$N$89&",")))} -> 2 | I12: {=SUMPRODUCT(ISNUMBER(SEARCH(", "&A12&",",", "&Riesgos!$N$4:$N$89&","))*(Riesgos!$J$4:$J$89="CRÍTICO"))} -> 1 | J12: {=SUMPRODUCT(ISNUMBER(SEARCH(", "&A12&",",", "&Riesgos!$N$4:$N$89&","))*(Riesgos!$J$4:$J$89="MEDIO-ALTO"))} -> 0
A13: PA-10 | B13: Completar el expediente de gobierno: actas del Comité de los trimestres II a IV de 2024; actas de ratificación de la Junta del Manual, la matriz de riesgo, la herramienta de listas, los Programas 2024 y 2025 y el Informe de Gestión 2024; memorial del Programa 2024 y sello de recibido del Programa 2025; e informes a la Junta. | C13: PAC / CD | D13: Alta | E13: Secretaría del Comité / Oficial de Cumplimiento | F13: 15 días | G13: Expediente de gobierno completo | H13: {=SUMPRODUCT(--ISNUMBER(SEARCH(", "&A13&",",", "&Riesgos!$N$4:$N$89&",")))} -> 5 | I13: {=SUMPRODUCT(ISNUMBER(SEARCH(", "&A13&",",", "&Riesgos!$N$4:$N$89&","))*(Riesgos!$J$4:$J$89="CRÍTICO"))} -> 0 | J13: {=SUMPRODUCT(ISNUMBER(SEARCH(", "&A13&",",", "&Riesgos!$N$4:$N$89&","))*(Riesgos!$J$4:$J$89="MEDIO-ALTO"))} -> 1
A14: PA-11 | B14: Conciliar los reportes de efectivo y cuasi efectivo enviados a la UAF durante el período y conservar los acuses. | C14: RR | D14: Alta | E14: Oficial de Cumplimiento | F14: 30 días | G14: Conciliación y acuses | H14: {=SUMPRODUCT(--ISNUMBER(SEARCH(", "&A14&",",", "&Riesgos!$N$4:$N$89&",")))} -> 1 | I14: {=SUMPRODUCT(ISNUMBER(SEARCH(", "&A14&",",", "&Riesgos!$N$4:$N$89&","))*(Riesgos!$J$4:$J$89="CRÍTICO"))} -> 0 | J14: {=SUMPRODUCT(ISNUMBER(SEARCH(", "&A14&",",", "&Riesgos!$N$4:$N$89&","))*(Riesgos!$J$4:$J$89="MEDIO-ALTO"))} -> 0
A15: PA-12 | B15: Aprobar el reglamento del Comité de Cumplimiento (quórum de directores, calendario trimestral, temas mínimos) e iniciar el informe trimestral a la Junta, con el consolidado de alertas y ROS. | C15: GC | D15: Alta | E15: Junta Directiva / Secretaría | F15: 60 días | G15: Reglamento; calendario; primer informe | H15: {=SUMPRODUCT(--ISNUMBER(SEARCH(", "&A15&",",", "&Riesgos!$N$4:$N$89&",")))} -> 3 | I15: {=SUMPRODUCT(ISNUMBER(SEARCH(", "&A15&",",", "&Riesgos!$N$4:$N$89&","))*(Riesgos!$J$4:$J$89="CRÍTICO"))} -> 0 | J15: {=SUMPRODUCT(ISNUMBER(SEARCH(", "&A15&",",", "&Riesgos!$N$4:$N$89&","))*(Riesgos!$J$4:$J$89="MEDIO-ALTO"))} -> 2
... A34: PA-31 | B34: Documentar la evaluación de riesgo del canal web y exigir evaluación previa para nuevos productos, canales y tecnologías. | C34: ER | D34: Media | E34: Oficial de Cumplimiento | F34: 180 días | G34: Evaluación documentada | H34: {=SUMPRODUCT(--ISNUMBER(SEARCH(", "&A34&",",", "&Riesgos!$N$4:$N$89&",")))} -> 1 | I34: {=SUMPRODUCT(ISNUMBER(SEARCH(", "&A34&",",", "&Riesgos!$N$4:$N$89&","))*(Riesgos!$J$4:$J$89="CRÍTICO"))} -> 0 | J34: {=SUMPRODUCT(ISNUMBER(SEARCH(", "&A34&",",", "&Riesgos!$N$4:$N$89&","))*(Riesgos!$J$4:$J$89="MEDIO-ALTO"))} -> 1
