Workbook

Sheet Variables
A1: ASEGURADORA ANCÓN, S.A. – VARIABLES DE VALORACIÓN DE RIESGOS BC/FT/FPADM
A2: Evaluación Independiente 2024-2025 | Preparado por: José A. Serrano | 02 abril 2026 (actualizado 02 octubre 2026)
A4: ESCALA DE PROBABILIDAD
A5: Nombre | B5: Descripción | E5: Puntaje
A6: Frecuente | B6: La probabilidad de ocurrencia del riesgo es muy alta; sucede en la mayoría de las circunstancias. | E6: 5
A7: Probable | B7: Es probable que el riesgo ocurra; los controles o procesos no son suficientemente efectivos para prevenirlo. | E7: 4
A8: Ocasional | B8: Existe la posibilidad de que el riesgo ocurra; los controles de mitigación no son del todo efectivos. | E8: 3
A9: Posible | B9: Existe una posibilidad limitada de que el riesgo ocurra; es poco probable con los controles actuales. | E9: 2
A10: Improbable | B10: La probabilidad de materialización es extremadamente baja; los controles son altamente efectivos. | E10: 1
A12: ESCALA DE IMPACTO
A13: Nombre | B13: Descripción | E13: Puntaje
A14: Catastrófico | B14: La materialización causaría impacto severo e irreversible: sanciones regulatorias mayores, pérdidas masivas, daño reputacional crítico. | E14: 5
A15: Mayor | B15: Generaría pérdidas o sanciones significativas, requiriendo intervención inmediata de la alta gerencia y la Junta Directiva. | E15: 4
A16: Moderado | B16: Impacto considerable: puede afectar operaciones o comprometer el cumplimiento regulatorio de forma parcial. | E16: 3
A17: Menor | B17: Impacto leve; genera correcciones administrativas menores sin afectar operaciones críticas. | E17: 2
A18: Insignificante | B18: Impacto mínimo sobre la operación; se resuelve con controles normales sin mayor afectación. | E18: 1
A20: TABLA DE NIVELES DE RIESGO (P × I)
A21: CLAVE (PROB:IMP) | B21: NIVEL DE RIESGO | C21: PUNTAJE P×I
A22: 5:1 | B22: MEDIO | C22: 5
A23: 5:2 | B23: MEDIO-ALTO | C23: 10
A24: 5:3 | B24: CRÍTICO | C24: 15
A25: 5:4 | B25: CRÍTICO | C25: 20
A26: 5:5 | B26: CRÍTICO | C26: 25
A27: 4:1 | B27: MEDIO | C27: 4
A28: 4:2 | B28: MEDIO-ALTO | C28: 8
A29: 4:3 | B29: MEDIO-ALTO | C29: 12
A30: 4:4 | B30: CRÍTICO | C30: 16
A31: 4:5 | B31: CRÍTICO | C31: 20
A32: 3:1 | B32: BAJO | C32: 3
A33: 3:2 | B33: MEDIO | C33: 6
... A46: 1:5 | B46: MEDIO | C46: 5
A47: OM | B47: OPT. DE MEJORA | C47: N/A
A49: DESCRIPCIÓN DE NIVELES DE RIESGO
A50: Nivel | B50: Descripción / Acción Requerida | E50: Puntaje P×I
A51: BAJO | B51: Riesgo aceptable. Controles mínimos son suficientes. Monitoreo semestral. | E51: 1 – 3
A52: MEDIO | B52: Riesgo manejable. Requiere medidas correctivas (60-90 días). Monitoreo trimestral. | E52: 4 – 6
A53: MEDIO-ALTO | B53: Riesgo significativo. Requiere plan de acción formal (30-60 días). Monitoreo mensual. | E53: 8 – 12
A54: CRÍTICO | B54: Riesgo inaceptable. Acción inmediata (0-30 días). Reporte obligatorio a JD y Oficial de Cumplimiento. | E54: 15 – 25
A55: OPT. DE MEJORA | B55: No es hallazgo de incumplimiento. Mejora preventiva o de adecuación normativa prospectiva. | E55: N/A

Sheet Riesgos
A1: ASEGURADORA ANCÓN, S.A. – MATRIZ DE RIESGO GSM – EVALUACIÓN INDEPENDIENTE 2024-2025
A2: Período: 1 julio 2024 – 30 junio 2025 | Elaborado: José A. Serrano | Versión inicial: 02 de abril de 2026 | Actualizada: octubre de 2026 (corte de evidencia: cuadro de control octubre 2026)
A3: DESCRIPCIÓN DEL HALLAZGO / OPORTUNIDAD DE MEJORA | B3: TIPO | C3: DOCUMENTO(S) AFECTADO(S) | D3: OBSERVACIÓN / NOTA GSM (actualizada oct-2026) | E3: PROBABILIDAD | F3: PROB. PUNT. | G3: IMPACTO | H3: IMP. PUNT. | I3: CALIFIC. P:I | J3: NIVEL DE RIESGO | K3: COMPONENTE | L3: BASE NORMATIVA / REFERENCIA | M3: PUNTAJE P×I | N3: PLAN DE ACCIÓN / FASE | O3: ACCIÓN REQUERIDA SEGÚN NIVEL
A4: GC-01 · Oficial de Cumplimiento con doble función y sin apoyo profesional. La Oficial de Cumplimiento también dirige el área Legal, rol en el que reporta al Gerente General. El Departamento cuenta con una asistente de apoyo administrativo, pero no con personal profesional para monitoreo, debida diligencia ni gestión de alertas. La SSRP ya había señalado esta situación en la inspección DSR-0924-2023 y no se ha corregido. | B4: Brecha | C4: Organigramas sep-2025; Resolución OAL-362; hojas de vida del Departamento; Informe SSRP DSR-0924-2023 | D4: Validado: la asistente administrativa no resuelve la dedicación exclusiva ni la falta de apoyo profesional. | E4: Probable | F4: =IFERROR(VLOOKUP(E4,Variables!$A$6:$E$10,5,0),"") -> 4 | G4: Mayor | H4: =IFERROR(VLOOKUP(G4,Variables!$A$14:$E$18,5,0),"") -> 4 | I4: =IF(B4="Oportunidad de Mejora","OM",IFERROR(CONCATENATE(F4,":",H4),"")) -> 4:4 | J4: =IFERROR(VLOOKUP(I4,Variables!$A$22:$B$47,2,FALSE()),"Por definir") -> CRÍTICO | K4: Gobierno Corporativo | L4: Acuerdo 03-2022, Arts. 5, 7 (num. 11), 8, 10 (párr. final) y 62 (num. 9, lit. b) | M4: =IF(I4="OM","N/A",IFERROR(F4*H4,"")) -> 16 | N4: PA-01 | O4: =IFERROR(VLOOKUP(J4,Variables!$A$51:$B$55,2,FALSE()),"") -> Riesgo inaceptable. Acción inmediata (0-30 días). Reporte obligatorio a JD y Oficial de Cumplimiento.
A5: GC-02 · Sin estudio de capacidad del Departamento de Cumplimiento. No existe un estudio que demuestre que los recursos humanos y tecnológicos de Cumplimiento son suficientes para el volumen de clientes, alertas y debidas diligencias de la aseguradora. | B5: Brecha | C5: Organigrama del Departamento de Cumplimiento | D5: Descripción de puesto pendiente de entrega; no se cuenta con análisis de capacidad. | E5: Ocasional | F5: =IFERROR(VLOOKUP(E5,Variables!$A$6:$E$10,5,0),"") -> 3 | G5: Moderado | H5: =IFERROR(VLOOKUP(G5,Variables!$A$14:$E$18,5,0),"") -> 3 | I5: =IF(B5="Oportunidad de Mejora","OM",IFERROR(CONCATENATE(F5,":",H5),"")) -> 3:3 | J5: =IFERROR(VLOOKUP(I5,Variables!$A$22:$B$47,2,FALSE()),"Por definir") -> MEDIO-ALTO | K5: Gobierno Corporativo | L5: Acuerdo 03-2022, Arts. 5 y 62 (num. 9, lit. d) | M5: =IF(I5="OM","N/A",IFERROR(F5*H5,"")) -> 9 | N5: PA-25 | O5: =IFERROR(VLOOKUP(J5,Variables!$A$51:$B$55,2,FALSE()),"") -> Riesgo significativo. Requiere plan de acción formal (30-60 días). Monitoreo mensual.
A6: GC-03 · Comité sin calendario ni temario y sin actas entre abril 2024 y mayo 2025. El Reglamento permitía sesionar con dos de seis integrantes, incluso sin directores. La convocatoria y la agenda dependían de la Oficial de Cumplimiento, a quien el Comité supervisa, y no existían calendario anual ni temario mínimo. Ancón indica que entre la sesión del 17 de abril de 2024 y la del 28 de mayo de 2025 hubo sesiones de seguimiento sin nuevas aprobaciones, pero sus actas no han sido aportadas, de modo que el mínimo de dos sesiones anuales que el Reglamento fijaba para 2024 no puede verificarse documentalmente. | B6: Brecha | C6: AA_GOBCORP03; actas 17-04-2024 y 28-05-2025; Cuadro de Trazabilidad | D6: Actas II a IV trimestre 2024 pendientes de entrega (sesiones de seguimiento según la aclaración). Ancón indicó que no existen calendario ni temario. | E6: Probable | F6: =IFERROR(VLOOKUP(E6,Variables!$A$6:$E$10,5,0),"") -> 4 | G6: Moderado | H6: =IFERROR(VLOOKUP(G6,Variables!$A$14:$E$18,5,0),"") -> 3 | I6: =IF(B6="Oportunidad de Mejora","OM",IFERROR(CONCATENATE(F6,":",H6),"")) -> 4:3 | J6: =IFERROR(VLOOKUP(I6,Variables!$A$22:$B$47,2,FALSE()),"Por definir") -> MEDIO-ALTO | K6: Gobierno Corporativo | L6: Reglamento AA_GOBCORP03; Acuerdo 03-2022, Arts. 10 (num. 14) y 11 | M6: =IF(I6="OM","N/A",IFERROR(F6*H6,"")) -> 12 | N6: PA-12 | O6: =IFERROR(VLOOKUP(J6,Variables!$A$51:$B$55,2,FALSE()),"") -> Riesgo significativo. Requiere plan de acción formal (30-60 días). Monitoreo mensual.
A7: GC-04 · Sin informes del Comité a la Junta y autoevaluación sin soporte. El Reglamento no definía periodicidad, formato ni contenido del reporte del Comité a la Junta; no se aportaron informes a la Junta, y Ancón indicó que no existe un informe anual de gestión del Comité. La autoevaluación de octubre de 2025 es un buen comienzo, pero sus 19 respuestas afirmativas no tienen soporte, la hoja de resumen marca 0 % por un error de fórmulas y no está firmada ni fue presentada a la Junta. | B7: Brecha | C7: AA_GOBCORP03; autoevaluación del Comité 01-10-2025 | D7: Informes a Junta pendientes de entrega; memorandos a Gerencia: Ancón indicó que no existen. | E7: Ocasional | F7: =IFERROR(VLOOKUP(E7,Variables!$A$6:$E$10,5,0),"") -> 3 | G7: Moderado | H7: =IFERROR(VLOOKUP(G7,Variables!$A$14:$E$18,5,0),"") -> 3 | I7: =IF(B7="Oportunidad de Mejora","OM",IFERROR(CONCATENATE(F7,":",H7),"")) -> 3:3 | J7: =IFERROR(VLOOKUP(I7,Variables!$A$22:$B$47,2,FALSE()),"Por definir") -> MEDIO-ALTO | K7: Gobierno Corporativo | L7: Acuerdo 03-2022, Art. 10 (nums. 14 y 15) | M7: =IF(I7="OM","N/A",IFERROR(F7*H7,"")) -> 9 | N7: PA-12, PA-26 | O7: =IFERROR(VLOOKUP(J7,Variables!$A$51:$B$55,2,FALSE()),"") -> Riesgo significativo. Requiere plan de acción formal (30-60 días). Monitoreo mensual.
A8: GC-05 · Código de Ética incompleto y sin política de partes relacionadas. El Código de Ética (AIN-28-CODETI, noviembre de 2023) existe, pero no incluye un procedimiento para declarar y gestionar conflictos de interés, reglas para operaciones con partes vinculadas, un canal de denuncia confidencial con protección frente a represalias, un responsable de seguimiento ni consecuencias por incumplimiento; además, lo elaboró Auditoría Interna, que luego debe evaluarlo. Ancón indicó que no tiene una política de transacciones con partes relacionadas, y en las entrevistas el personal no identificó un canal de denuncia anónimo. | B8: Brecha | C8: AIN-28-CODETI; entrevistas | D8: Política de partes relacionadas: Ancón indicó que no existe. | E8: Ocasional | F8: =IFERROR(VLOOKUP(E8,Variables!$A$6:$E$10,5,0),"") -> 3 | G8: Moderado | H8: =IFERROR(VLOOKUP(G8,Variables!$A$14:$E$18,5,0),"") -> 3 | I8: =IF(B8="Oportunidad de Mejora","OM",IFERROR(CONCATENATE(F8,":",H8),"")) -> 3:3 | J8: =IFERROR(VLOOKUP(I8,Variables!$A$22:$B$47,2,FALSE()),"Por definir") -> MEDIO-ALTO | K8: Gobierno Corporativo | L8: Manual del Sistema de Control Interno, secc. 6.1; Ley 23 de 2015, Art. 57; Acuerdo 03-2022, Art. 15 (num. 8); Recomendación 18 del GAFI | M8: =IF(I8="OM","N/A",IFERROR(F8*H8,"")) -> 9 | N8: PA-18 | O8: =IFERROR(VLOOKUP(J8,Variables!$A$51:$B$55,2,FALSE()),"") -> Riesgo significativo. Requiere plan de acción formal (30-60 días). Monitoreo mensual.
A9: GC-06 · Debilidades de trazabilidad en documentos de gobierno. El acta de Junta del 20-01-2021 aprueba un reglamento sin identificar código ni versión, no muestra firmas y cita un "Acuerdo 22" que no corresponde; la lista de integrantes del Comité no está al día; el Manual del Sistema de Control Interno V2.0 aún remite a normas de la Superintendencia Financiera de Colombia; y el Manual de RR.HH. no indica quién lo aprobó. | B9: Brecha | C9: Acta JD 20-01-2021; AA_GOBCORP03; AIN-28-MSCI-1; GESREHU-1 | D9: Revisado. | E9: Ocasional | F9: =IFERROR(VLOOKUP(E9,Variables!$A$6:$E$10,5,0),"") -> 3 | G9: Menor | H9: =IFERROR(VLOOKUP(G9,Variables!$A$14:$E$18,5,0),"") -> 2 | I9: =IF(B9="Oportunidad de Mejora","OM",IFERROR(CONCATENATE(F9,":",H9),"")) -> 3:2 | J9: =IFERROR(VLOOKUP(I9,Variables!$A$22:$B$47,2,FALSE()),"Por definir") -> MEDIO | K9: Gobierno Corporativo | L9: Manual del Sistema de Control Interno, secc. 6.1; Acuerdo 03-2022, Arts. 11 y 14 | M9: =IF(I9="OM","N/A",IFERROR(F9*H9,"")) -> 6 | N9: PA-22 | O9: =IFERROR(VLOOKUP(J9,Variables!$A$51:$B$55,2,FALSE()),"") -> Riesgo manejable. Requiere medidas correctivas (60-90 días). Monitoreo trimestral.
A10: GC-07 · Planificación de Auditoría Interna sin enfoque de riesgo explícito. El Plan de Auditoría Interna 2024 no muestra una planificación basada en riesgos ni los elementos formales de aprobación, alcance, recursos y reprogramación de trabajos. Como aspecto positivo, Ancón aportó un informe anual de Auditoría Interna al Departamento de Cumplimiento; recomendamos que la revisión de Cumplimiento quede programada de forma expresa en cada plan anual. | B10: Brecha | C10: Planes de Auditoría Interna 2024 y 2025; Informe de Auditoría Interna al Dpto. de Cumplimiento | D10: Informe de Auditoría Interna al Dpto. de Cumplimiento aportado. | E10: Posible | F10: =IFERROR(VLOOKUP(E10,Variables!$A$6:$E$10,5,0),"") -> 2 | G10: Moderado | H10: =IFERROR(VLOOKUP(G10,Variables!$A$14:$E$18,5,0),"") -> 3 | I10: =IF(B10="Oportunidad de Mejora","OM",IFERROR(CONCATENATE(F10,":",H10),"")) -> 2:3 | J10: =IFERROR(VLOOKUP(I10,Variables!$A$22:$B$47,2,FALSE()),"Por definir") -> MEDIO | K10: Gobierno Corporativo | L10: Ley 23 de 2015, Art. 45; Acuerdo 03-2022, Art. 18 | M10: =IF(I10="OM","N/A",IFERROR(F10*H10,"")) -> 6 | N10: PA-21 | O10: =IFERROR(VLOOKUP(J10,Variables!$A$51:$B$55,2,FALSE()),"") -> Riesgo manejable. Requiere medidas correctivas (60-90 días). Monitoreo trimestral.
A11: GC-08 · Sin suplente ni continuidad de la función de prevención. No hay un suplente designado ni un plan que asegure la continuidad de la función de prevención si la Oficial de Cumplimiento se ausenta. | B11: Brecha | C11: Organigrama; Manual de Prevención | D11: No evidenciado. | E11: Posible | F11: =IFERROR(VLOOKUP(E11,Variables!$A$6:$E$10,5,0),"") -> 2 | G11: Moderado | H11: =IFERROR(VLOOKUP(G11,Variables!$A$14:$E$18,5,0),"") -> 3 | I11: =IF(B11="Oportunidad de Mejora","OM",IFERROR(CONCATENATE(F11,":",H11),"")) -> 2:3 | J11: =IFERROR(VLOOKUP(I11,Variables!$A$22:$B$47,2,FALSE()),"Por definir") -> MEDIO | K11: Gobierno Corporativo | L11: Acuerdo 03-2022, Art. 9 | M11: =IF(I11="OM","N/A",IFERROR(F11*H11,"")) -> 6 | N11: PA-27 | O11: =IFERROR(VLOOKUP(J11,Variables!$A$51:$B$55,2,FALSE()),"") -> Riesgo manejable. Requiere medidas correctivas (60-90 días). Monitoreo trimestral.
A12: GC-09 · Vacantes en funciones que sostienen el modelo de prevención. Están vacantes o concentradas las posiciones de Oficial de Protección de Datos, Gerencia de Recursos Humanos y una gerencia propia para Emisión. | B12: Brecha | C12: Organigrama general; entrevistas | D12: Confirmado en entrevistas. | E12: Ocasional | F12: =IFERROR(VLOOKUP(E12,Variables!$A$6:$E$10,5,0),"") -> 3 | G12: Menor | H12: =IFERROR(VLOOKUP(G12,Variables!$A$14:$E$18,5,0),"") -> 2 | I12: =IF(B12="Oportunidad de Mejora","OM",IFERROR(CONCATENATE(F12,":",H12),"")) -> 3:2 | J12: =IFERROR(VLOOKUP(I12,Variables!$A$22:$B$47,2,FALSE()),"Por definir") -> MEDIO | K12: Gobierno Corporativo | L12: Ley 81 de 2019; Acuerdo 03-2022, Art. 16 | M12: =IF(I12="OM","N/A",IFERROR(F12*H12,"")) -> 6 | N12: PA-27 | O12: =IFERROR(VLOOKUP(J12,Variables!$A$51:$B$55,2,FALSE()),"") -> Riesgo manejable. Requiere medidas correctivas (60-90 días). Monitoreo trimestral.
A13: GC-10 · Designación del Oficial sin acta de Junta ni descripción de puesto. Para la designación de la Oficial de Cumplimiento se cuenta con la Resolución OAL-362 de 30 de diciembre de 2022; el acta de Junta Directiva que la designa y la descripción del puesto están pendientes de entrega. | B13: Brecha | C13: Resolución OAL-362 | D13: Acta de Junta y descripción de puesto pendientes de entrega. | E13: Posible | F13: =IFERROR(VLOOKUP(E13,Variables!$A$6:$E$10,5,0),"") -> 2 | G13: Moderado | H13: =IFERROR(VLOOKUP(G13,Variables!$A$14:$E$18,5,0),"") -> 3 | I13: =IF(B13="Oportunidad de Mejora","OM",IFERROR(CONCATENATE(F13,":",H13),"")) -> 2:3 | J13: =IFERROR(VLOOKUP(I13,Variables!$A$22:$B$47,2,FALSE()),"Por definir") -> MEDIO | K13: Gobierno Corporativo | L13: Acuerdo 03-2022, Arts. 5 y 8 | M13: =IF(I13="OM","N/A",IFERROR(F13*H13,"")) -> 6 | N13: PA-01 | O13: =IFERROR(VLOOKUP(J13,Variables!$A$51:$B$55,2,FALSE()),"") -> Riesgo manejable. Requiere medidas correctivas (60-90 días). Monitoreo trimestral.
A14: GC-11 · Ratificación de la Junta Directiva sin evidencia concluyente. La aclaración de Ancón documenta las aprobaciones del Comité, pero la ratificación por la Junta Directiva del Manual de Prevención, de la matriz de riesgo y de la herramienta de listas no está evidenciada, y las actas de Junta aportadas sobre los Programas 2024 y 2025 y el Informe de Gestión 2024 están sujetas a confirmación con la Oficial de Cumplimiento. | B14: Brecha | C14: Aclaración de aprobaciones del Comité; actas de Junta aportadas | D14: Actas de Junta del Manual, la matriz y la herramienta de listas pendientes de entrega; las demás, sujetas a confirmación. | E14: Ocasional | F14: =IFERROR(VLOOKUP(E14,Variables!$A$6:$E$10,5,0),"") -> 3 | G14: Moderado | H14: =IFERROR(VLOOKUP(G14,Variables!$A$14:$E$18,5,0),"") -> 3 | I14: =IF(B14="Oportunidad de Mejora","OM",IFERROR(CONCATENATE(F14,":",H14),"")) -> 3:3 | J14: =IFERROR(VLOOKUP(I14,Variables!$A$22:$B$47,2,FALSE()),"Por definir") -> MEDIO-ALTO | K14: Gobierno Corporativo | L14: Acuerdo 03-2022, Arts. 11, 12, 13, 14 y 15 (aprobación del Comité y ratificación de la Junta) | M14: =IF(I14="OM","N/A",IFERROR(F14*H14,"")) -> 9 | N14: PA-10 | O14: =IFERROR(VLOOKUP(J14,Variables!$A$51:$B$55,2,FALSE()),"") -> Riesgo significativo. Requiere plan de acción formal (30-60 días). Monitoreo mensual.
A15: PP-01 · Manual describe la consulta en listas solo para alto riesgo. El Manual describe la consulta en listas OFAC y ONU solo para clientes de alto riesgo, aspecto que la SSRP observó en 2022. En la práctica, Ancón aportó evidencia de la herramienta de consulta, de barridos sobre la cartera existente y de pólizas rechazadas o canceladas por coincidencias, por lo que la brecha es principalmente documental: el Manual debe reflejar que el control se aplica a todos. | B15: Brecha | C15: MPREMET-21; CONCLI-15; herramienta de listas; constancia de barridos | D15: Validado con evidencia de barridos del período: el control opera; falta alinear el texto del Manual. | E15: Posible | F15: =IFERROR(VLOOKUP(E15,Variables!$A$6:$E$10,5,0),"") -> 2 | G15: Moderado | H15: =IFERROR(VLOOKUP(G15,Variables!$A$14:$E$18,5,0),"") -> 3 | I15: =IF(B15="Oportunidad de Mejora","OM",IFERROR(CONCATENATE(F15,":",H15),"")) -> 2:3 | J15: =IFERROR(VLOOKUP(I15,Variables!$A$22:$B$47,2,FALSE()),"Por definir") -> MEDIO | K15: Políticas y Procedimientos | L15: Ley 23 de 2015, Art. 49; Acuerdo 03-2022, Arts. 21 (num. 2) y 23 (num. 9) | M15: =IF(I15="OM","N/A",IFERROR(F15*H15,"")) -> 6 | N15: PA-06 | O15: =IFERROR(VLOOKUP(J15,Variables!$A$51:$B$55,2,FALSE()),"") -> Riesgo manejable. Requiere medidas correctivas (60-90 días). Monitoreo trimestral.
... A89: RM-24 · Planes de actualización de expedientes (Art. 7, lits. f y g). Formalizar ambos planes con metas trimestrales y reportarlos en el informe trimestral. | B89: Oportunidad de Mejora | C89: PAC / DD | D89: Qué cambia: Planes de actualización de clientes con operaciones inconsistentes y de colaboradores, con informe a Comité y Junta. Situación en Ancón: Expedientes de colaboradores desactualizados (DD-08). | E89: Posible | F89: =IFERROR(VLOOKUP(E89,Variables!$A$6:$E$10,5,0),"") -> 2 | G89: Moderado | H89: =IFERROR(VLOOKUP(G89,Variables!$A$14:$E$18,5,0),"") -> 3 | I89: =IF(B89="Oportunidad de Mejora","OM",IFERROR(CONCATENATE(F89,":",H89),"")) -> OM | J89: =IFERROR(VLOOKUP(I89,Variables!$A$22:$B$47,2,FALSE()),"Por definir") -> OPT. DE MEJORA | K89: Hoja de ruta Acuerdo 07-2025 | L89: Acuerdo SSRP 07-2025 (fuera del alcance; valor agregado) | M89: =IF(I89="OM","N/A",IFERROR(F89*H89,"")) -> N/A | N89: Fase 2 | O89: =IFERROR(VLOOKUP(J89,Variables!$A$51:$B$55,2,FALSE()),"") -> No es hallazgo de incumplimiento. Mejora preventiva o de adecuación normativa prospectiva.

Sheet Matriz de Riesgos
A1: MAPA DE RIESGO – ASEGURADORA ANCÓN, S.A. (Probabilidad × Impacto)
A2: Los valores de cada celda son generados automáticamente desde la hoja Riesgos | COUNTIF(Riesgos!$I$4:$I$120) | Evaluación Independiente 2024-2025 (actualizada octubre 2026)
A3: PROBABILIDAD ↓ / IMPACTO → | C3: 1 Insignificante | D3: 2 Menor | E3: 3 Moderado | F3: 4 Mayor | G3: 5 Catastrófico
A4: 5 Frecuente | B4: 5 | C4: =COUNTIF(Riesgos!$I$4:$I$120,"5:1") -> 0 | D4: =COUNTIF(Riesgos!$I$4:$I$120,"5:2") -> 0 | E4: =COUNTIF(Riesgos!$I$4:$I$120,"5:3") -> 1 | F4: =COUNTIF(Riesgos!$I$4:$I$120,"5:4") -> 1 | G4: =COUNTIF(Riesgos!$I$4:$I$120,"5:5") -> 0
A5: 4 Probable | B5: 4 | C5: =COUNTIF(Riesgos!$I$4:$I$120,"4:1") -> 0 | D5: =COUNTIF(Riesgos!$I$4:$I$120,"4:2") -> 0 | E5: =COUNTIF(Riesgos!$I$4:$I$120,"4:3") -> 6 | F5: =COUNTIF(Riesgos!$I$4:$I$120,"4:4") -> 5 | G5: =COUNTIF(Riesgos!$I$4:$I$120,"4:5") -> 0
A6: 3 Ocasional | B6: 3 | C6: =COUNTIF(Riesgos!$I$4:$I$120,"3:1") -> 0 | D6: =COUNTIF(Riesgos!$I$4:$I$120,"3:2") -> 11 | E6: =COUNTIF(Riesgos!$I$4:$I$120,"3:3") -> 14 | F6: =COUNTIF(Riesgos!$I$4:$I$120,"3:4") -> 1 | G6: =COUNTIF(Riesgos!$I$4:$I$120,"3:5") -> 1
A7: 2 Posible | B7: 2 | C7: =COUNTIF(Riesgos!$I$4:$I$120,"2:1") -> 1 | D7: =COUNTIF(Riesgos!$I$4:$I$120,"2:2") -> 7 | E7: =COUNTIF(Riesgos!$I$4:$I$120,"2:3") -> 9 | F7: =COUNTIF(Riesgos!$I$4:$I$120,"2:4") -> 1 | G7: =COUNTIF(Riesgos!$I$4:$I$120,"2:5") -> 0
A8: 1 Improbable | B8: 1 | C8: =COUNTIF(Riesgos!$I$4:$I$120,"1:1") -> 0 | D8: =COUNTIF(Riesgos!$I$4:$I$120,"1:2") -> 1 | E8: =COUNTIF(Riesgos!$I$4:$I$120,"1:3") -> 0 | F8: =COUNTIF(Riesgos!$I$4:$I$120,"1:4") -> 0 | G8: =COUNTIF(Riesgos!$I$4:$I$120,"1:5") -> 0
B9: Score | C9: 1 | D9: 2 | E9: 3 | F9: 4 | G9: 5
A11: LEYENDA DE NIVELES DE RIESGO
A12: CRÍTICO | B12: P×I ≥ 15 | C12: Acción inmediata (0-30 días). Reporte obligatorio a Junta Directiva y Oficial de Cumplimiento.
A13: MEDIO-ALTO | B13: P×I 8-12 | C13: Plan de acción formal (30-60 días). Monitoreo mensual.
A14: MEDIO | B14: P×I 4-6 | C14: Medidas correctivas (60-90 días). Monitoreo trimestral.
A15: BAJO | B15: P×I 1-3 | C15: Riesgo aceptable con controles mínimos. Monitoreo semestral.
A16: OPT. DE MEJORA | B16: N/A | C16: No es hallazgo de incumplimiento. Mejora preventiva o adecuación normativa prospectiva.
A18: RESUMEN – BRECHAS Y OPORTUNIDADES DE MEJORA (Período: julio 2024 – junio 2025)
A19: Brechas CRÍTICAS | G19: =COUNTIF(Riesgos!$J$4:$J$120,"CRÍTICO") -> 8
A20: Brechas MEDIO-ALTO | G20: =COUNTIF(Riesgos!$J$4:$J$120,"MEDIO-ALTO") -> 22
A21: Brechas MEDIAS | G21: =COUNTIF(Riesgos!$J$4:$J$120,"MEDIO") -> 27
A22: Brechas BAJAS | G22: =COUNTIF(Riesgos!$J$4:$J$120,"BAJO") -> 2
A23: Oportunidades de Mejora | G23: =COUNTIF(Riesgos!$J$4:$J$120,"OPT. DE MEJORA") -> 27
A24: TOTAL HALLAZGOS (Brechas) | G24: =COUNTIF(Riesgos!$B$4:$B$120,"Brecha") -> 59
A25: TOTAL REGISTROS EN MATRIZ | G25: =COUNTA(Riesgos!$A$4:$A$120) -> 86
A27: RESUMEN POR COMPONENTE – BRECHAS DEL PERÍODO (julio 2024 – junio 2025)
A28: Componente | D28: CRÍTICO | E28: MEDIO-ALTO | F28: MEDIO | G28: BAJO | H28: TOTAL
A29: Gobierno Corporativo | D29: =COUNTIFS(Riesgos!$K$4:$K$120,$A29,Riesgos!$J$4:$J$120,"CRÍTICO") -> 1 | E29: =COUNTIFS(Riesgos!$K$4:$K$120,$A29,Riesgos!$J$4:$J$120,"MEDIO-ALTO") -> 5 | F29: =COUNTIFS(Riesgos!$K$4:$K$120,$A29,Riesgos!$J$4:$J$120,"MEDIO") -> 5 | G29: =COUNTIFS(Riesgos!$K$4:$K$120,$A29,Riesgos!$J$4:$J$120,"BAJO") -> 0 | H29: =SUM(D29:G29) -> 11
A30: Políticas y Procedimientos | D30: =COUNTIFS(Riesgos!$K$4:$K$120,$A30,Riesgos!$J$4:$J$120,"CRÍTICO") -> 0 | E30: =COUNTIFS(Riesgos!$K$4:$K$120,$A30,Riesgos!$J$4:$J$120,"MEDIO-ALTO") -> 2 | F30: =COUNTIFS(Riesgos!$K$4:$K$120,$A30,Riesgos!$J$4:$J$120,"MEDIO") -> 7 | G30: =COUNTIFS(Riesgos!$K$4:$K$120,$A30,Riesgos!$J$4:$J$120,"BAJO") -> 1 | H30: =SUM(D30:G30) -> 10
A31: Programa Anual de Cumplimiento | D31: =COUNTIFS(Riesgos!$K$4:$K$120,$A31,Riesgos!$J$4:$J$120,"CRÍTICO") -> 0 | E31: =COUNTIFS(Riesgos!$K$4:$K$120,$A31,Riesgos!$J$4:$J$120,"MEDIO-ALTO") -> 2 | F31: =COUNTIFS(Riesgos!$K$4:$K$120,$A31,Riesgos!$J$4:$J$120,"MEDIO") -> 4 | G31: =COUNTIFS(Riesgos!$K$4:$K$120,$A31,Riesgos!$J$4:$J$120,"BAJO") -> 0 | H31: =SUM(D31:G31) -> 6
A32: Monitoreo Transaccional | D32: =COUNTIFS(Riesgos!$K$4:$K$120,$A32,Riesgos!$J$4:$J$120,"CRÍTICO") -> 1 | E32: =COUNTIFS(Riesgos!$K$4:$K$120,$A32,Riesgos!$J$4:$J$120,"MEDIO-ALTO") -> 5 | F32: =COUNTIFS(Riesgos!$K$4:$K$120,$A32,Riesgos!$J$4:$J$120,"MEDIO") -> 1 | G32: =COUNTIFS(Riesgos!$K$4:$K$120,$A32,Riesgos!$J$4:$J$120,"BAJO") -> 1 | H32: =SUM(D32:G32) -> 8
A33: Debida Diligencia | D33: =COUNTIFS(Riesgos!$K$4:$K$120,$A33,Riesgos!$J$4:$J$120,"CRÍTICO") -> 3 | E33: =COUNTIFS(Riesgos!$K$4:$K$120,$A33,Riesgos!$J$4:$J$120,"MEDIO-ALTO") -> 4 | F33: =COUNTIFS(Riesgos!$K$4:$K$120,$A33,Riesgos!$J$4:$J$120,"MEDIO") -> 1 | G33: =COUNTIFS(Riesgos!$K$4:$K$120,$A33,Riesgos!$J$4:$J$120,"BAJO") -> 0 | H33: =SUM(D33:G33) -> 8
A34: Evaluación de Riesgo AML | D34: =COUNTIFS(Riesgos!$K$4:$K$120,$A34,Riesgos!$J$4:$J$120,"CRÍTICO") -> 1 | E34: =COUNTIFS(Riesgos!$K$4:$K$120,$A34,Riesgos!$J$4:$J$120,"MEDIO-ALTO") -> 1 | F34: =COUNTIFS(Riesgos!$K$4:$K$120,$A34,Riesgos!$J$4:$J$120,"MEDIO") -> 3 | G34: =COUNTIFS(Riesgos!$K$4:$K$120,$A34,Riesgos!$J$4:$J$120,"BAJO") -> 0 | H34: =SUM(D34:G34) -> 5
A35: Reportes Regulatorios | D35: =COUNTIFS(Riesgos!$K$4:$K$120,$A35,Riesgos!$J$4:$J$120,"CRÍTICO") -> 2 | E35: =COUNTIFS(Riesgos!$K$4:$K$120,$A35,Riesgos!$J$4:$J$120,"MEDIO-ALTO") -> 2 | F35: =COUNTIFS(Riesgos!$K$4:$K$120,$A35,Riesgos!$J$4:$J$120,"MEDIO") -> 2 | G35: =COUNTIFS(Riesgos!$K$4:$K$120,$A35,Riesgos!$J$4:$J$120,"BAJO") -> 0 | H35: =SUM(D35:G35) -> 6
A36: Conservación de Documentos | D36: =COUNTIFS(Riesgos!$K$4:$K$120,$A36,Riesgos!$J$4:$J$120,"CRÍTICO") -> 0 | E36: =COUNTIFS(Riesgos!$K$4:$K$120,$A36,Riesgos!$J$4:$J$120,"MEDIO-ALTO") -> 1 | F36: =COUNTIFS(Riesgos!$K$4:$K$120,$A36,Riesgos!$J$4:$J$120,"MEDIO") -> 4 | G36: =COUNTIFS(Riesgos!$K$4:$K$120,$A36,Riesgos!$J$4:$J$120,"BAJO") -> 0 | H36: =SUM(D36:G36) -> 5
A37: TOTAL | D37: =SUM(D29:D36) -> 8 | E37: =SUM(E29:E36) -> 22 | F37: =SUM(F29:F36) -> 27 | G37: =SUM(G29:G36) -> 2 | H37: =SUM(H29:H36) -> 59
A39: Nota: las oportunidades de mejora (OM) no se califican como brechas. Las RM corresponden a la hoja de ruta hacia el Acuerdo SSRP 07-2025, que está fuera del alcance de la evaluación del período y se incluye como valor agregado.
